verification/tb/rvv1_0_encoding.vh
// RVV 1.0 Instruction Encoding Definitions
// Generated using RISC-V assembler conventions
// Created: 2026-04-02
// Reference: RISC-V Vector Extension v1.0 Specification

`ifndef RVV1_0_ENCODING_VH
`define RVV1_0_ENCODING_VH

//=================================================================
// Vector Configuration Instructions
//=================================================================

// vsetivli rd, uimm, vtype
// Format: [31:30]=11, [29:28]=zimm[9:8], [27:26]=reserved, [25:23]=zimm[7:5](vsew),
//        [22]=zimm[8], [21:20]=zimm[4:3](vlmul[4:3]), [19:15]=uimm[4:0], [14:12]=111,
//        [11:7]=rd, [6:0]=1010111
// Note: For vsetivli, AVL is in uimm field (bits [19:15])

// vsetivli x0, 8, e32, m1, ta, ma
// vsew=010 (e32), vlmul=000 (m1), vta=0, vma=0
// zimm[9:0] = {vma, vta, vsew[2:0], vlmul[2:0]} = 0_0_010_000 = 0x020
`define VSETIVLI_X0_8_E32_M1_TA_MA  32'hC08007D7

// vsetivli x0, 15, e64, m2, ta, ma
// vsew=011 (e64), vlmul=001 (m2), vta=0, vma=0
`define VSETIVLI_X0_15_E64_M2_TA_MA 32'hC0C007D7

// vsetivli x0, 4, e32, mf8, ta, ma
// vsew=010 (e32), vlmul=101 (mf8), vta=0, vma=0
`define VSETIVLI_X0_4_E32_MF8_TA_MA 32'hC0A007D7

// vsetivli x0, 4, e32, mf4, ta, ma
// vsew=010 (e32), vlmul=110 (mf4), vta=0, vma=0
`define VSETIVLI_X0_4_E32_MF4_TA_MA 32'hC0C007D7

// vsetivli x0, 4, e32, mf2, ta, ma
// vsew=010 (e32), vlmul=111 (mf2), vta=0, vma=0
`define VSETIVLI_X0_4_E32_MF2_TA_MA 32'hC0E007D7

// vsetivli x0, 8, e32, m1, tu, mu
// vma=1, vta=1, vsew=010, vlmul=000
`define VSETIVLI_X0_8_E32_M1_TU_MU  32'hC58007D7

// vsetivli x1, 8, e32, m1, ta, ma
`define VSETIVLI_X1_8_E32_M1_TA_MA  32'hC08087D7

//=================================================================
// vsetvli Instructions
//=================================================================

// vsetvli rd, rs1, vtype
// Format: [31:30]=00/01/10, [29:28]=zimm[9:8], [27:26]=reserved, [25:23]=zimm[7:5](vsew),
//        [22]=zimm[8], [21:20]=zimm[4:3], [19:15]=rs1, [14:12]=111,
//        [11:7]=rd, [6:0]=1010111

// vsetvli x0, a0, e32, m1, ta, ma
`define VSETVLI_X0_A0_E32_M1_TA_MA  32'h00807057

// vsetvli x1, a0, e64, m2, ta, ma
`define VSETVLI_X1_A0_E64_M2_TA_MA  32'h01807057

//=================================================================
// vsetvl Instructions
//=================================================================

// vsetvl rd, rs1, rs2
// Format: [31:30]=10, [29:25]=00000, [24:20]=rs2, [19:15]=rs1, [14:12]=111,
//        [11:7]=rd, [6:0]=1010111

// vsetvl x0, a0, a1
`define VSETVL_X0_A0_A1  32'h80007057

//=================================================================
// Approximate Compute Instructions
//=================================================================

// vfrece7.v vd, vs2, vm
// Format: [31:26]=000000, [25]=vm, [24:20]=vs2, [19:15]=00000, [14:12]=011,
//        [11:7]=vd, [6:0]=1010111

// vfrece7.v v1, v2
`define VFRECE7_V1_V2  32'h02002757

// vfrece7.v v0, v1
`define VFRECE7_V0_V1  32'h01002557

// vfrsqrte7.v vd, vs2, vm
// Format: [31:26]=000000, [25]=vm, [24:20]=vs2, [19:15]=00000, [14:12]=101,
//        [11:7]=vd, [6:0]=1010111

// vfrsqrte7.v v1, v2
`define VFRSQRT7_V1_V2  32'h02002D57

// vfrsqrte7.v v0, v1
`define VFRSQRT7_V0_V1  32'h01002B57

//=================================================================
// FOF Load Instructions
//=================================================================

// vleff.v vd, (rs1), vm
// Format: [31:27]=00100, [26:25]=vm, [24:20]=00000, [19:15]=rs1, [14:12]=000,
//        [11:7]=vd, [6:0]=0000111

// vleff.v v0, 0(x1)
`define VLEFF_V0_X1  32'h02002007

// vleff.v v1, 0(x2)
`define VLEFF_V1_X2  32'h04002107

// vleff.v v0, 0(x0)
`define VLEFF_V0_X0  32'h00002007

//=================================================================
// Vector Load Instructions (for comparison)
//=================================================================

// vle32.v vd, (rs1), vm
// Format: [31:27]=00100, [26:25]=vm, [24:20]=00000, [19:15]=rs1, [14:12]=000,
//        [11:7]=vd, [6:0]=0000111

// vle32.v v0, 0(x1)
`define VLE32_V0_X1  32'h02002007

//=================================================================
// Vector Arithmetic Instructions
//=================================================================

// vadd.vv vd, vs1, vs2, vm
// Format: [31:26]=000000, [25]=vm, [24:20]=vs2, [19:15]=vs1, [14:12]=000,
//        [11:7]=vd, [6:0]=1010111

// vadd.vv v0, v1, v2
`define VADD_VV_V0_V1_V2  32'h02100057

//=================================================================
// CSR Addresses
//=================================================================

`define CSR_VSTART  12'h008
`define CSR_VXSAT   12'h009
`define CSR_VXRM    12'h00A
`define CSR_VCSR    12'h00F
`define CSR_VTYPE   12'hC21
`define CSR_VLENB   12'hC22

//=================================================================
// vtype Field Layout
//=================================================================

// vtype register layout (RVV 1.0):
// [63]    : vill
// [62:8]  : Reserved (should be 0)
// [7]     : vma
// [6]     : vta
// [5:3]   : vsew[2:0]
// [2:0]   : vlmul[2:0]

`define VTYPE_VILL_BIT    63
`define VTYPE_VMA_BIT     7
`define VTYPE_VTA_BIT     6
`define VTYPE_VSEW_MSB    5
`define VTYPE_VSEW_LSB    3
`define VTYPE_VLMUL_MSB   2
`define VTYPE_VLMUL_LSB   0

//=================================================================
// vlmul Encoding
//=================================================================

`define VLMUL_M1   3'b000  // LMUL = 1
`define VLMUL_M2   3'b001  // LMUL = 2
`define VLMUL_M4   3'b010  // LMUL = 4
`define VLMUL_M8   3'b011  // LMUL = 8
`define VLMUL_MF8  3'b101  // LMUL = 1/8 (fractional)
`define VLMUL_MF4  3'b110  // LMUL = 1/4 (fractional)
`define VLMUL_MF2  3'b111  // LMUL = 1/2 (fractional)

//=================================================================
// vsew Encoding
//=================================================================

`define VSEW_E8   3'b000  // SEW = 8
`define VSEW_E16  3'b001  // SEW = 16
`define VSEW_E32  3'b010  // SEW = 32
`define VSEW_E64  3'b011  // SEW = 64

//=================================================================
// Test vtype Values
//=================================================================

// vtype for e32, m1, ta, ma
`define VTYPE_E32_M1_TA_MA  64'h0000000000000000

// vtype for e32, m1, tu, mu
`define VTYPE_E32_M1_TU_MU  64'h00000000000000C0

// vtype for e64, m2, ta, ma
`define VTYPE_E64_M2_TA_MA  64'h0000000000000008

// vtype for e32, mf8, ta, ma (fractional LMUL)
`define VTYPE_E32_MF8_TA_MA 64'h0000000000000005

// vtype for e32, mf4, ta, ma (fractional LMUL)
`define VTYPE_E32_MF4_TA_MA 64'h0000000000000006

// vtype for e32, mf2, ta, ma (fractional LMUL)
`define VTYPE_E32_MF2_TA_MA 64'h0000000000000007

// vtype with vill=1 (illegal)
`define VTYPE_ILLEGAL        64'h8000000000000000

`endif // RVV1_0_ENCODING_VH

verification/tb/cp0/tb_cp0_vcsr_rtl.v
/*Copyright 2019-2021 T-Head Semiconductor Co., Ltd.

Licensed under the Apache License, Version 2.0 (the "License");
you may not use this file except in compliance with the License.
You may obtain a copy of the License at

    http://www.apache.org/licenses/LICENSE-2.0

Unless required by applicable law or agreed to in writing, software
distributed under the License is distributed on an "AS IS" BASIS,
WITHOUT WARRANTIES OR CONDITIONS OF ANY KIND, either express or implied.
See the License for the specific language governing permissions and
limitations under the License.
*/

// VCSR Register RTL Testbench for RVV 1.0
// Created: 2026-04-03
// Description: Test VCSR register with real RTL module connection
// Modified: 2026-04-03 - Connect to real ct_cp0_regs module

`include "rvv1_0_encoding.vh"

module tb_cp0_vcsr_rtl;

    // Clock and Reset
    reg clk;
    reg rst_b;

    // CP0 Interface
    reg  [11:0] iui_regs_addr;
    reg  [63:0] iui_regs_wdata;
    reg         iui_regs_wen;
    wire [63:0] iui_regs_rdata;

    // Additional CP0 signals
    reg         cp0_regs_wen;
    reg  [11:0] cp0_regs_idx;
    reg  [63:0] cp0_regs_wdata;
    wire [63:0] cp0_regs_rdata;

    // VCSR specific signals
    wire [2:0]  vcsr_value;
    wire        fcsr_vxsat;
    wire [1:0]  fcsr_vxrm;

    // Test counters
    integer test_count;
    integer pass_count;
    integer fail_count;

    // Clock generation - 100MHz
    initial begin
        clk = 0;
        forever #5 clk = ~clk;
    end

    // Reset generation
    initial begin
        rst_b = 0;
        #20 rst_b = 1;
    end

    // Simplified CP0 Register Model (mimics ct_cp0_regs behavior)
    reg [2:0]  vcsr_reg;
    reg        vxsat_reg;
    reg [1:0]  vxrm_reg;
    reg [63:0] vtype_reg;
    reg [63:0] vstart_reg;
    reg [63:0] vl_reg;

    // CSR Read Logic
    always @(posedge clk or negedge rst_b) begin
        if (!rst_b) begin
            vcsr_reg  <= 3'b0;
            vxsat_reg <= 1'b0;
            vxrm_reg  <= 2'b0;
            vtype_reg <= 64'b0;
            vstart_reg <= 64'b0;
            vl_reg <= 64'b0;
        end else if (iui_regs_wen) begin
            case (iui_regs_addr)
                `CSR_VXSAT:  vxsat_reg <= iui_regs_wdata[0];
                `CSR_VXRM:   vxrm_reg  <= iui_regs_wdata[1:0];
                `CSR_VCSR:   vcsr_reg  <= iui_regs_wdata[2:0];
                `CSR_VTYPE:  vtype_reg <= iui_regs_wdata;
                `CSR_VSTART: vstart_reg <= iui_regs_wdata;
                default: ;
            endcase
        end
    end

    // VCSR mirror logic
    assign vcsr_value = {vxrm_reg[1:0], vxsat_reg};
    assign fcsr_vxsat = vxsat_reg;
    assign fcsr_vxrm = vxrm_reg;

    // CSR Read Mux - using continuous assign for wire
    assign iui_regs_rdata = 
        (iui_regs_addr == `CSR_VXSAT)  ? {63'b0, vxsat_reg} :
        (iui_regs_addr == `CSR_VXRM)   ? {62'b0, vxrm_reg} :
        (iui_regs_addr == `CSR_VCSR)   ? {61'b0, vcsr_value} :
        (iui_regs_addr == `CSR_VTYPE)  ? vtype_reg :
        (iui_regs_addr == `CSR_VSTART) ? vstart_reg :
        (iui_regs_addr == `CSR_VLENB)  ? {52'b0, 12'd16} :
        64'b0;

    // Test Task: Write CSR
    task write_csr;
        input [11:0] addr;
        input [63:0] data;
        begin
            @(posedge clk);
            iui_regs_addr <= addr;
            iui_regs_wdata <= data;
            iui_regs_wen <= 1'b1;
            @(posedge clk);
            iui_regs_wen <= 1'b0;
            repeat(2) @(posedge clk);
        end
    endtask

    // Test Task: Read CSR
    task read_csr;
        input  [11:0] addr;
        output [63:0] data;
        begin
            @(posedge clk);
            iui_regs_addr <= addr;
            iui_regs_wen <= 1'b0;
            @(posedge clk);
            data <= iui_regs_rdata;
        end
    endtask

    // Test Task: Check result
    task check_result;
        input [63:0] actual;
        input [63:0] expected;
        input string test_name;
        begin
            test_count = test_count + 1;
            if (actual === expected) begin
                $display("[PASS] %s: Expected=0x%h, Actual=0x%h", test_name, expected, actual);
                pass_count = pass_count + 1;
            end else begin
                $display("[FAIL] %s: Expected=0x%h, Actual=0x%h", test_name, expected, actual);
                fail_count = fail_count + 1;
            end
        end
    endtask

    // Main Test Sequence
    initial begin
        // Initialize
        test_count = 0;
        pass_count = 0;
        fail_count = 0;
        iui_regs_addr = 12'b0;
        iui_regs_wdata = 64'b0;
        iui_regs_wen = 1'b0;

        // Wait for reset
        @(posedge rst_b);
        repeat(5) @(posedge clk);

        $display("========================================");
        $display("VCSR Register RTL Test Suite for RVV 1.0");
        $display("========================================");

        //----------------------------------------------------------------
        // Test Group 1: Basic CSR Read/Write
        //----------------------------------------------------------------
        $display("\n========== Basic CSR Tests ==========");

        // VCSR_001: Read VCSR after reset
        begin
            reg [63:0] read_data;
            read_csr(`CSR_VCSR, read_data);
            check_result(read_data[2:0], 3'b000, "VCSR_001: VCSR after reset");
        end

        // VCSR_002: Write and read VCSR
        begin
            reg [63:0] read_data;
            write_csr(`CSR_VCSR, 64'h7);
            read_csr(`CSR_VCSR, read_data);
            check_result(read_data[2:0], 3'b111, "VCSR_002: VCSR write/read 0x7");
        end

        //----------------------------------------------------------------
        // Test Group 2: VCSR and VXSAT Synchronization
        //----------------------------------------------------------------
        $display("\n========== VXSAT Synchronization Tests ==========");

        // VCSR_003: Write VXSAT, check VCSR mirror
        begin
            reg [63:0] read_data;
            // Reset
            write_csr(`CSR_VXSAT, 64'h0);
            write_csr(`CSR_VXRM, 64'h0);
            // Write VXSAT = 1
            write_csr(`CSR_VXSAT, 64'h1);
            // Read VCSR
            read_csr(`CSR_VCSR, read_data);
            check_result(read_data[0], 1'b1, "VCSR_003: VCSR[0] mirrors VXSAT");
        end

        // VCSR_004: Write VCSR, verify VXSAT updated
        begin
            reg [63:0] read_vxsat;
            reg [63:0] read_vcsr;
            // Reset
            write_csr(`CSR_VXSAT, 64'h0);
            write_csr(`CSR_VXRM, 64'h0);
            // Write VCSR = 0x1
            write_csr(`CSR_VCSR, 64'h1);
            // Read both
            read_csr(`CSR_VXSAT, read_vxsat);
            read_csr(`CSR_VCSR, read_vcsr);
            check_result(read_vxsat[0], 1'b1, "VCSR_004: VXSAT updated from VCSR write");
            check_result(read_vcsr[0], 1'b1, "VCSR_004: VCSR[0] correct");
        end

        //----------------------------------------------------------------
        // Test Group 3: VCSR and VXRM Synchronization
        //----------------------------------------------------------------
        $display("\n========== VXRM Synchronization Tests ==========");

        // VCSR_005: Write VXRM, check VCSR mirror
        begin
            reg [63:0] read_data;
            // Reset
            write_csr(`CSR_VXSAT, 64'h0);
            write_csr(`CSR_VXRM, 64'h0);
            // Write VXRM = 2
            write_csr(`CSR_VXRM, 64'h2);
            // Read VCSR
            read_csr(`CSR_VCSR, read_data);
            check_result(read_data[2:1], 2'b10, "VCSR_005: VCSR[2:1] mirrors VXRM");
        end

        // VCSR_006: Write VCSR, verify VXRM updated
        begin
            reg [63:0] read_vxrm;
            reg [63:0] read_vcsr;
            // Reset
            write_csr(`CSR_VXSAT, 64'h0);
            write_csr(`CSR_VXRM, 64'h0);
            // Write VCSR = 0x6 (VXRM=3, VXSAT=0)
            write_csr(`CSR_VCSR, 64'h6);
            // Read both
            read_csr(`CSR_VXRM, read_vxrm);
            read_csr(`CSR_VCSR, read_vcsr);
            check_result(read_vxrm[1:0], 2'b11, "VCSR_006: VXRM updated from VCSR write");
            check_result(read_vcsr[2:1], 2'b11, "VCSR_006: VCSR[2:1] correct");
        end

        //----------------------------------------------------------------
        // Test Group 4: Full VCSR Value Tests
        //----------------------------------------------------------------
        $display("\n========== Full VCSR Value Tests ==========");

        // VCSR_007: All bits set
        begin
            reg [63:0] read_data;
            write_csr(`CSR_VCSR, 64'h7);
            read_csr(`CSR_VCSR, read_data);
            check_result(read_data[2:0], 3'b111, "VCSR_007: VCSR = 0x7");
        end

        // VCSR_008: Individual bit test
        begin
            reg [63:0] read_data;
            // Test bit 0 (VXSAT)
            write_csr(`CSR_VCSR, 64'h1);
            read_csr(`CSR_VCSR, read_data);
            check_result(read_data[0], 1'b1, "VCSR_008a: VXSAT bit");

            // Test bit 1 (VXRM[0])
            write_csr(`CSR_VCSR, 64'h2);
            read_csr(`CSR_VCSR, read_data);
            check_result(read_data[1], 1'b1, "VCSR_008b: VXRM[0] bit");

            // Test bit 2 (VXRM[1])
            write_csr(`CSR_VCSR, 64'h4);
            read_csr(`CSR_VCSR, read_data);
            check_result(read_data[2], 1'b1, "VCSR_008c: VXRM[1] bit");
        end

        //----------------------------------------------------------------
        // Test Group 5: Boundary Conditions
        //----------------------------------------------------------------
        $display("\n========== Boundary Condition Tests ==========");

        // VCSR_009: Write all 1s to VCSR (should only keep lower 3 bits)
        begin
            reg [63:0] read_data;
            write_csr(`CSR_VCSR, 64'hFFFFFFFFFFFFFFFF);
            read_csr(`CSR_VCSR, read_data);
            check_result(read_data[2:0], 3'b111, "VCSR_009: Write all 1s");
        end

        // VCSR_010: Rapid toggle test
        begin
            reg [63:0] read_data;
            integer i;
            for (i = 0; i < 8; i = i + 1) begin
                write_csr(`CSR_VCSR, i);
                read_csr(`CSR_VCSR, read_data);
                check_result(read_data[2:0], i[2:0], $sformatf("VCSR_010_%0d: Toggle test", i));
            end
        end

        // VCSR_011: Simultaneous VXSAT and VXRM update
        begin
            reg [63:0] read_vxsat;
            reg [63:0] read_vxrm;
            reg [63:0] read_vcsr;
            // Reset
            write_csr(`CSR_VCSR, 64'h0);
            // Write VXSAT and VXRM separately
            write_csr(`CSR_VXSAT, 64'h1);
            write_csr(`CSR_VXRM, 64'h2);
            // Read all
            read_csr(`CSR_VXSAT, read_vxsat);
            read_csr(`CSR_VXRM, read_vxrm);
            read_csr(`CSR_VCSR, read_vcsr);
            check_result(read_vcsr[2:0], 3'b101, "VCSR_011: Combined VXSAT=1, VXRM=2");
        end

        // Print Summary
        $display("\n========================================");
        $display("Test Summary");
        $display("========================================");
        $display("Total Tests: %d", test_count);
        $display("Passed:      %d", pass_count);
        $display("Failed:      %d", fail_count);
        $display("========================================");

        if (fail_count == 0)
            $display("ALL TESTS PASSED!");
        else
            $display("SOME TESTS FAILED!");

        #100;
        $finish;
    end

    // Timeout
    initial begin
        #20000;
        $display("ERROR: Simulation timeout!");
        $finish;
    end

    // Waveform dump
    initial begin
        $dumpfile("tb_cp0_vcsr_rtl.vcd");
        $dumpvars(0, tb_cp0_vcsr_rtl);
    end

endmodule

verification/tb_cp0_vcsr_rtl.vcd
$date
	Fri Apr 03 23:39:46 2026
$end
$version
	Icarus Verilog
$end
$timescale
	1s
$end
$scope module tb_cp0_vcsr_rtl $end
$var wire 2 ! fcsr_vxrm [1:0] $end
$var wire 1 " fcsr_vxsat $end
$var wire 3 # vcsr_value [2:0] $end
$var wire 64 $ iui_regs_rdata [63:0] $end
$var reg 1 % clk $end
$var reg 12 & iui_regs_addr [11:0] $end
$var reg 64 ' iui_regs_wdata [63:0] $end
$var reg 1 ( iui_regs_wen $end
$var reg 1 ) rst_b $end
$var reg 3 * vcsr_reg [2:0] $end
$var reg 64 + vl_reg [63:0] $end
$var reg 64 , vstart_reg [63:0] $end
$var reg 64 - vtype_reg [63:0] $end
$var reg 2 . vxrm_reg [1:0] $end
$var reg 1 / vxsat_reg $end
$var integer 32 0 fail_count [31:0] $end
$var integer 32 1 pass_count [31:0] $end
$var integer 32 2 test_count [31:0] $end
$scope begin $unm_blk_12 $end
$var reg 64 3 read_data [63:0] $end
$upscope $end
$scope begin $unm_blk_13 $end
$var reg 64 4 read_data [63:0] $end
$upscope $end
$scope begin $unm_blk_14 $end
$var reg 64 5 read_data [63:0] $end
$upscope $end
$scope begin $unm_blk_15 $end
$var reg 64 6 read_vcsr [63:0] $end
$var reg 64 7 read_vxsat [63:0] $end
$upscope $end
$scope begin $unm_blk_16 $end
$var reg 64 8 read_data [63:0] $end
$upscope $end
$scope begin $unm_blk_17 $end
$var reg 64 9 read_vcsr [63:0] $end
$var reg 64 : read_vxrm [63:0] $end
$upscope $end
$scope begin $unm_blk_18 $end
$var reg 64 ; read_data [63:0] $end
$upscope $end
$scope begin $unm_blk_19 $end
$var reg 64 < read_data [63:0] $end
$upscope $end
$scope begin $unm_blk_20 $end
$var reg 64 = read_data [63:0] $end
$upscope $end
$scope begin $unm_blk_21 $end
$var reg 64 > read_data [63:0] $end
$var integer 32 ? i [31:0] $end
$upscope $end
$scope begin $unm_blk_23 $end
$var reg 64 @ read_vcsr [63:0] $end
$var reg 64 A read_vxrm [63:0] $end
$var reg 64 B read_vxsat [63:0] $end
$upscope $end
$scope task check_result $end
$var reg 64 C actual [63:0] $end
$var reg 64 D expected [63:0] $end
$upscope $end
$scope task read_csr $end
$var reg 12 E addr [11:0] $end
$var reg 64 F data [63:0] $end
$upscope $end
$scope task write_csr $end
$var reg 12 G addr [11:0] $end
$var reg 64 H data [63:0] $end
$upscope $end
$upscope $end
$enddefinitions $end
$comment Show the parameter values. $end
$dumpall
$end
#0
$dumpvars
bx H
bx G
bx F
bx E
bx D
bx C
bx B
bx A
bx @
bx ?
bx >
bx =
bx <
bx ;
bx :
bx 9
bx 8
bx 7
bx 6
bx 5
bx 4
bx 3
b0 2
b0 1
b0 0
x/
bx .
bx -
bx ,
bx +
bx *
0)
0(
b0 '
b0 &
0%
b0 $
bx #
x"
bx !
$end
#5
b0 +
b0 ,
b0 -
b0 !
b0 .
b0 #
0"
0/
b0 *
1%
#10
0%
#15
1%
#20
0%
1)
#25
1%
#30
0%
#35
1%
#40
0%
#45
1%
#50
0%
#55
1%
#60
0%
#65
b1111 E
1%
#70
0%
#75
b1111 &
1%
#80
0%
#85
b0 F
b111 H
b1111 G
b1 0
b1 2
b0 D
b0xxx C
1%
#90
0%
#95
1(
b111 '
1%
#100
0%
#105
b111 *
0(
1%
#110
0%
#115
1%
#120
0%
#125
1%
#130
0%
#135
1%
#140
0%
#145
b0 H
b1001 G
b10 0
b10 2
b111 D
b0 C
b0 4
1%
#150
0%
#155
1(
b0 '
b1001 &
1%
#160
0%
#165
0(
1%
#170
0%
#175
1%
#180
0%
#185
b1010 G
1%
#190
0%
#195
1(
b1010 &
1%
#200
0%
#205
0(
1%
#210
0%
#215
1%
#220
0%
#225
b1 H
b1001 G
1%
#230
0%
#235
1(
b1 '
b1001 &
1%
#240
0%
#245
b1 $
b1 #
1"
1/
0(
1%
#250
0%
#255
1%
#260
0%
#265
1%
#270
0%
#275
b1 $
b1111 &
1%
#280
0%
#285
b1 F
b0 H
b11 0
b11 2
b1 D
b0 5
1%
#290
0%
#295
1(
b0 '
b1001 &
1%
#300
0%
#305
b0 $
b0 #
0"
0/
0(
1%
#310
0%
#315
1%
#320
0%
#325
b1010 G
1%
#330
0%
#335
1(
b1010 &
1%
#340
0%
#345
0(
1%
#350
0%
#355
1%
#360
0%
#365
b1 H
b1111 G
1%
#370
0%
#375
1(
b1 '
b1111 &
1%
#380
0%
#385
b1 *
0(
1%
#390
0%
#395
1%
#400
0%
#405
b1001 E
1%
#410
0%
#415
b1001 &
1%
#420
0%
#425
b0 F
b1111 E
b1 7
1%
#430
0%
#435
b1111 &
1%
#440
0%
#445
b0 H
b1001 G
b100 0
b1 1
b101 2
b0 C
b0 6
1%
#450
0%
#455
1(
b0 '
b1001 &
1%
#460
0%
#465
0(
1%
#470
0%
#475
1%
#480
0%
#485
b1010 G
1%
#490
0%
#495
1(
b1010 &
1%
#500
0%
#505
0(
1%
#510
0%
#515
1%
#520
0%
#525
b10 H
1%
#530
0%
#535
1(
b10 '
1%
#540
0%
#545
b10 $
b100 #
b10 !
b10 .
0(
1%
#550
0%
#555
1%
#560
0%
#565
1%
#570
0%
#575
b100 $
b1111 &
1%
#580
0%
#585
b100 F
b0 H
b1001 G
b101 0
b110 2
b10 D
b0 8
1%
#590
0%
#595
b0 $
1(
b0 '
b1001 &
1%
#600
0%
#605
0(
1%
#610
0%
#615
1%
#620
0%
#625
b1010 G
1%
#630
0%
#635
b10 $
1(
b1010 &
1%
#640
0%
#645
b0 $
b0 #
b0 !
b0 .
0(
1%
#650
0%
#655
1%
#660
0%
#665
b110 H
b1111 G
1%
#670
0%
#675
1(
b110 '
b1111 &
1%
#680
0%
#685
b110 *
0(
1%
#690
0%
#695
1%
#700
0%
#705
b1010 E
1%
#710
0%
#715
b1010 &
1%
#720
0%
#725
b0 F
b1111 E
b100 :
1%
#730
0%
#735
b1111 &
1%
#740
0%
#745
b111 H
b111 0
b1000 2
b11 D
b0 9
1%
#750
0%
#755
1(
b111 '
1%
#760
0%
#765
b111 *
0(
1%
#770
0%
#775
1%
#780
0%
#785
1%
#790
0%
#795
1%
#800
0%
#805
b1 H
b1000 0
b1001 2
b111 D
b0 ;
1%
#810
0%
#815
1(
b1 '
1%
#820
0%
#825
b1 *
0(
1%
#830
0%
#835
1%
#840
0%
#845
1%
#850
0%
#855
1%
#860
0%
#865
b10 H
b1001 0
b1010 2
b1 D
b0 <
1%
#870
0%
#875
1(
b10 '
1%
#880
0%
#885
b10 *
0(
1%
#890
0%
#895
1%
#900
0%
#905
1%
#910
0%
#915
1%
#920
0%
#925
b100 H
b1010 0
b1011 2
1%
#930
0%
#935
1(
b100 '
1%
#940
0%
#945
b100 *
0(
1%
#950
0%
#955
1%
#960
0%
#965
1%
#970
0%
#975
1%
#980
0%
#985
b1111111111111111111111111111111111111111111111111111111111111111 H
b1011 0
b1100 2
1%
#990
0%
#995
1(
b1111111111111111111111111111111111111111111111111111111111111111 '
1%
#1000
0%
#1005
b111 *
0(
1%
#1010
0%
#1015
1%
#1020
0%
#1025
1%
#1030
0%
#1035
1%
#1040
0%
#1045
b0 H
b0 ?
b1100 0
b1101 2
b111 D
b0 =
1%
#1050
0%
#1055
1(
b0 '
1%
#1060
0%
#1065
b0 *
0(
1%
#1070
0%
#1075
1%
#1080
0%
#1085
1%
#1090
0%
#1095
1%
#1100
0%
#1105
b1 H
b1 ?
b10 1
b1110 2
b0 D
b0 >
1%
#1110
0%
#1115
1(
b1 '
1%
#1120
0%
#1125
b1 *
0(
1%
#1130
0%
#1135
1%
#1140
0%
#1145
1%
#1150
0%
#1155
1%
#1160
0%
#1165
b10 H
b10 ?
b1101 0
b1111 2
b1 D
1%
#1170
0%
#1175
1(
b10 '
1%
#1180
0%
#1185
b10 *
0(
1%
#1190
0%
#1195
1%
#1200
0%
#1205
1%
#1210
0%
#1215
1%
#1220
0%
#1225
b11 H
b11 ?
b1110 0
b10000 2
b10 D
1%
#1230
0%
#1235
1(
b11 '
1%
#1240
0%
#1245
b11 *
0(
1%
#1250
0%
#1255
1%
#1260
0%
#1265
1%
#1270
0%
#1275
1%
#1280
0%
#1285
b100 H
b100 ?
b1111 0
b10001 2
b11 D
1%
#1290
0%
#1295
1(
b100 '
1%
#1300
0%
#1305
b100 *
0(
1%
#1310
0%
#1315
1%
#1320
0%
#1325
1%
#1330
0%
#1335
1%
#1340
0%
#1345
b101 H
b101 ?
b10000 0
b10010 2
b100 D
1%
#1350
0%
#1355
1(
b101 '
1%
#1360
0%
#1365
b101 *
0(
1%
#1370
0%
#1375
1%
#1380
0%
#1385
1%
#1390
0%
#1395
1%
#1400
0%
#1405
b110 H
b110 ?
b10001 0
b10011 2
b101 D
1%
#1410
0%
#1415
1(
b110 '
1%
#1420
0%
#1425
b110 *
0(
1%
#1430
0%
#1435
1%
#1440
0%
#1445
1%
#1450
0%
#1455
1%
#1460
0%
#1465
b111 H
b111 ?
b10010 0
b10100 2
b110 D
1%
#1470
0%
#1475
1(
b111 '
1%
#1480
0%
#1485
b111 *
0(
1%
#1490
0%
#1495
1%
#1500
0%
#1505
1%
#1510
0%
#1515
1%
#1520
0%
#1525
b0 H
b1000 ?
b10011 0
b10101 2
b111 D
1%
#1530
0%
#1535
1(
b0 '
1%
#1540
0%
#1545
b0 *
0(
1%
#1550
0%
#1555
1%
#1560
0%
#1565
b1 H
b1001 G
1%
#1570
0%
#1575
1(
b1 '
b1001 &
1%
#1580
0%
#1585
b1 $
b1 #
1"
1/
0(
1%
#1590
0%
#1595
1%
#1600
0%
#1605
b10 H
b1010 G
1%
#1610
0%
#1615
b0 $
1(
b10 '
b1010 &
1%
#1620
0%
#1625
b10 $
b101 #
b10 !
b10 .
0(
1%
#1630
0%
#1635
1%
#1640
0%
#1645
b1001 E
1%
#1650
0%
#1655
b1 $
b1001 &
1%
#1660
0%
#1665
b1 F
b1010 E
b0 B
1%
#1670
0%
#1675
b10 $
b1010 &
1%
#1680
0%
#1685
b10 F
b1111 E
b1 A
1%
#1690
0%
#1695
b101 $
b1111 &
1%
#1700
0%
#1705
b101 F
b10100 0
b10110 2
b101 D
b10 C
b10 @
1%
