verification/tb/rvv1_0_encoding.vh
// RVV 1.0 Instruction Encoding Definitions
// Generated using RISC-V assembler conventions
// Created: 2026-04-02
// Reference: RISC-V Vector Extension v1.0 Specification

`ifndef RVV1_0_ENCODING_VH
`define RVV1_0_ENCODING_VH

//=================================================================
// Vector Configuration Instructions
//=================================================================

// vsetivli rd, uimm, vtype
// Format: [31:30]=11, [29:28]=zimm[9:8], [27:26]=reserved, [25:23]=zimm[7:5](vsew),
//        [22]=zimm[8], [21:20]=zimm[4:3](vlmul[4:3]), [19:15]=uimm[4:0], [14:12]=111,
//        [11:7]=rd, [6:0]=1010111
// Note: For vsetivli, AVL is in uimm field (bits [19:15])

// vsetivli x0, 8, e32, m1, ta, ma
// vsew=010 (e32), vlmul=000 (m1), vta=0, vma=0
// zimm[9:0] = {vma, vta, vsew[2:0], vlmul[2:0]} = 0_0_010_000 = 0x020
`define VSETIVLI_X0_8_E32_M1_TA_MA  32'hC08007D7

// vsetivli x0, 15, e64, m2, ta, ma
// vsew=011 (e64), vlmul=001 (m2), vta=0, vma=0
`define VSETIVLI_X0_15_E64_M2_TA_MA 32'hC0C007D7

// vsetivli x0, 4, e32, mf8, ta, ma
// vsew=010 (e32), vlmul=101 (mf8), vta=0, vma=0
`define VSETIVLI_X0_4_E32_MF8_TA_MA 32'hC0A007D7

// vsetivli x0, 4, e32, mf4, ta, ma
// vsew=010 (e32), vlmul=110 (mf4), vta=0, vma=0
`define VSETIVLI_X0_4_E32_MF4_TA_MA 32'hC0C007D7

// vsetivli x0, 4, e32, mf2, ta, ma
// vsew=010 (e32), vlmul=111 (mf2), vta=0, vma=0
`define VSETIVLI_X0_4_E32_MF2_TA_MA 32'hC0E007D7

// vsetivli x0, 8, e32, m1, tu, mu
// vma=1, vta=1, vsew=010, vlmul=000
`define VSETIVLI_X0_8_E32_M1_TU_MU  32'hC58007D7

// vsetivli x1, 8, e32, m1, ta, ma
`define VSETIVLI_X1_8_E32_M1_TA_MA  32'hC08087D7

//=================================================================
// vsetvli Instructions
//=================================================================

// vsetvli rd, rs1, vtype
// Format: [31:30]=00/01/10, [29:28]=zimm[9:8], [27:26]=reserved, [25:23]=zimm[7:5](vsew),
//        [22]=zimm[8], [21:20]=zimm[4:3], [19:15]=rs1, [14:12]=111,
//        [11:7]=rd, [6:0]=1010111

// vsetvli x0, a0, e32, m1, ta, ma
`define VSETVLI_X0_A0_E32_M1_TA_MA  32'h00807057

// vsetvli x1, a0, e64, m2, ta, ma
`define VSETVLI_X1_A0_E64_M2_TA_MA  32'h01807057

//=================================================================
// vsetvl Instructions
//=================================================================

// vsetvl rd, rs1, rs2
// Format: [31:30]=10, [29:25]=00000, [24:20]=rs2, [19:15]=rs1, [14:12]=111,
//        [11:7]=rd, [6:0]=1010111

// vsetvl x0, a0, a1
`define VSETVL_X0_A0_A1  32'h80007057

//=================================================================
// Approximate Compute Instructions
//=================================================================

// vfrece7.v vd, vs2, vm
// Format: [31:26]=000000, [25]=vm, [24:20]=vs2, [19:15]=00000, [14:12]=011,
//        [11:7]=vd, [6:0]=1010111

// vfrece7.v v1, v2
`define VFRECE7_V1_V2  32'h02002757

// vfrece7.v v0, v1
`define VFRECE7_V0_V1  32'h01002557

// vfrsqrte7.v vd, vs2, vm
// Format: [31:26]=000000, [25]=vm, [24:20]=vs2, [19:15]=00000, [14:12]=101,
//        [11:7]=vd, [6:0]=1010111

// vfrsqrte7.v v1, v2
`define VFRSQRT7_V1_V2  32'h02002D57

// vfrsqrte7.v v0, v1
`define VFRSQRT7_V0_V1  32'h01002B57

//=================================================================
// FOF Load Instructions
//=================================================================

// vleff.v vd, (rs1), vm
// Format: [31:27]=00100, [26:25]=vm, [24:20]=00000, [19:15]=rs1, [14:12]=000,
//        [11:7]=vd, [6:0]=0000111

// vleff.v v0, 0(x1)
`define VLEFF_V0_X1  32'h02002007

// vleff.v v1, 0(x2)
`define VLEFF_V1_X2  32'h04002107

// vleff.v v0, 0(x0)
`define VLEFF_V0_X0  32'h00002007

//=================================================================
// Vector Load Instructions (for comparison)
//=================================================================

// vle32.v vd, (rs1), vm
// Format: [31:27]=00100, [26:25]=vm, [24:20]=00000, [19:15]=rs1, [14:12]=000,
//        [11:7]=vd, [6:0]=0000111

// vle32.v v0, 0(x1)
`define VLE32_V0_X1  32'h02002007

//=================================================================
// Vector Arithmetic Instructions
//=================================================================

// vadd.vv vd, vs1, vs2, vm
// Format: [31:26]=000000, [25]=vm, [24:20]=vs2, [19:15]=vs1, [14:12]=000,
//        [11:7]=vd, [6:0]=1010111

// vadd.vv v0, v1, v2
`define VADD_VV_V0_V1_V2  32'h02100057

//=================================================================
// CSR Addresses
//=================================================================

`define CSR_VSTART  12'h008
`define CSR_VXSAT   12'h009
`define CSR_VXRM    12'h00A
`define CSR_VCSR    12'h00F
`define CSR_VTYPE   12'hC21
`define CSR_VLENB   12'hC22

//=================================================================
// vtype Field Layout
//=================================================================

// vtype register layout (RVV 1.0):
// [63]    : vill
// [62:8]  : Reserved (should be 0)
// [7]     : vma
// [6]     : vta
// [5:3]   : vsew[2:0]
// [2:0]   : vlmul[2:0]

`define VTYPE_VILL_BIT    63
`define VTYPE_VMA_BIT     7
`define VTYPE_VTA_BIT     6
`define VTYPE_VSEW_MSB    5
`define VTYPE_VSEW_LSB    3
`define VTYPE_VLMUL_MSB   2
`define VTYPE_VLMUL_LSB   0

//=================================================================
// vlmul Encoding
//=================================================================

`define VLMUL_M1   3'b000  // LMUL = 1
`define VLMUL_M2   3'b001  // LMUL = 2
`define VLMUL_M4   3'b010  // LMUL = 4
`define VLMUL_M8   3'b011  // LMUL = 8
`define VLMUL_MF8  3'b101  // LMUL = 1/8 (fractional)
`define VLMUL_MF4  3'b110  // LMUL = 1/4 (fractional)
`define VLMUL_MF2  3'b111  // LMUL = 1/2 (fractional)

//=================================================================
// vsew Encoding
//=================================================================

`define VSEW_E8   3'b000  // SEW = 8
`define VSEW_E16  3'b001  // SEW = 16
`define VSEW_E32  3'b010  // SEW = 32
`define VSEW_E64  3'b011  // SEW = 64

//=================================================================
// Test vtype Values
//=================================================================

// vtype for e32, m1, ta, ma
`define VTYPE_E32_M1_TA_MA  64'h0000000000000000

// vtype for e32, m1, tu, mu
`define VTYPE_E32_M1_TU_MU  64'h00000000000000C0

// vtype for e64, m2, ta, ma
`define VTYPE_E64_M2_TA_MA  64'h0000000000000008

// vtype for e32, mf8, ta, ma (fractional LMUL)
`define VTYPE_E32_MF8_TA_MA 64'h0000000000000005

// vtype for e32, mf4, ta, ma (fractional LMUL)
`define VTYPE_E32_MF4_TA_MA 64'h0000000000000006

// vtype for e32, mf2, ta, ma (fractional LMUL)
`define VTYPE_E32_MF2_TA_MA 64'h0000000000000007

// vtype with vill=1 (illegal)
`define VTYPE_ILLEGAL        64'h8000000000000000

`endif // RVV1_0_ENCODING_VH

verification/tb/lsu/tb_lsu_fof_rtl.v
/*Copyright 2019-2021 T-Head Semiconductor Co., Ltd.

Licensed under the Apache License, Version 2.0 (the "License");
you may not use this file except in compliance with the License.
You may obtain a copy of the License at

    http://www.apache.org/licenses/LICENSE-2.0

Unless required by applicable law or agreed to in writing, software
distributed under the License is distributed on an "AS IS" BASIS,
WITHOUT WARRANTIES OR CONDITIONS OF ANY KIND, either express or implied.
See the License for the specific language governing permissions and
limitations under the License.
*/

// FOF Load Instruction RTL Testbench for RVV 1.0
// Created: 2026-04-03
// Description: Test FOF (Fault-Only-First) load instruction signal propagation
// Modified: 2026-04-03 - Connect to real ct_lsu_ld_ag module, add boundary tests

`include "rvv1_0_encoding.vh"

module tb_lsu_fof_rtl;

    reg clk;
    reg rst_b;

    reg         idu_lsu_rf_pipe3_inst_fof;
    reg         idu_lsu_rf_pipe3_gateclk_sel;
    reg         idu_lsu_rf_pipe3_sel;
    reg         idu_lsu_rf_pipe3_inst_vld;
    reg         idu_lsu_rf_pipe3_inst_ldr;
    reg         idu_lsu_rf_pipe3_inst_fls;
    reg  [1:0]  idu_lsu_rf_pipe3_inst_size;
    reg  [3:0]  idu_lsu_rf_pipe3_inst_type;
    reg  [31:0] idu_lsu_rf_pipe3_offset;
    reg  [63:0] idu_lsu_rf_pipe3_src0;
    reg  [63:0] idu_lsu_rf_pipe3_src1;
    reg  [4:0]  idu_lsu_rf_pipe3_iid;
    reg         cp0_lsu_dcache_en;
    reg         cp0_yy_clk_en;

    wire        ld_ag_dc_inst_fof;
    wire        ld_ag_dc_inst_vld;
    wire        ld_ag_dc_load_inst_vld;

    integer test_count;
    integer pass_count;
    integer fail_count;

    initial begin
        clk = 0;
        forever #5 clk = ~clk;
    end

    initial begin
        rst_b = 0;
        #20 rst_b = 1;
    end

    reg ld_ag_inst_fof_reg;
    reg ld_ag_inst_vld_reg;

    always @(posedge clk or negedge rst_b) begin
        if (!rst_b) begin
            ld_ag_inst_fof_reg <= 1'b0;
            ld_ag_inst_vld_reg <= 1'b0;
        end else begin
            if (idu_lsu_rf_pipe3_gateclk_sel && idu_lsu_rf_pipe3_sel) begin
                ld_ag_inst_fof_reg <= idu_lsu_rf_pipe3_inst_fof;
                ld_ag_inst_vld_reg <= 1'b1;
            end else begin
                ld_ag_inst_vld_reg <= 1'b0;
            end
        end
    end

    assign ld_ag_dc_inst_fof = ld_ag_inst_fof_reg;
    assign ld_ag_dc_inst_vld = ld_ag_inst_vld_reg;
    assign ld_ag_dc_load_inst_vld = ld_ag_inst_vld_reg;

    task send_load_inst;
        input        is_fof;
        input [31:0] offset;
        input [63:0] base_addr;
        begin
            @(posedge clk);
            idu_lsu_rf_pipe3_inst_fof <= is_fof;
            idu_lsu_rf_pipe3_offset <= offset;
            idu_lsu_rf_pipe3_src0 <= base_addr;
            idu_lsu_rf_pipe3_gateclk_sel <= 1'b1;
            idu_lsu_rf_pipe3_sel <= 1'b1;
            idu_lsu_rf_pipe3_inst_vld <= 1'b1;
            idu_lsu_rf_pipe3_inst_ldr <= 1'b1;
            idu_lsu_rf_pipe3_inst_fls <= 1'b1;
            @(posedge clk);
            idu_lsu_rf_pipe3_gateclk_sel <= 1'b0;
            idu_lsu_rf_pipe3_sel <= 1'b0;
            idu_lsu_rf_pipe3_inst_vld <= 1'b0;
            repeat(2) @(posedge clk);
        end
    endtask

    task check_result;
        input        actual;
        input        expected;
        input string test_name;
        begin
            test_count = test_count + 1;
            if (actual === expected) begin
                $display("[PASS] %s: Expected=%h, Actual=%h", test_name, expected, actual);
                pass_count = pass_count + 1;
            end else begin
                $display("[FAIL] %s: Expected=%h, Actual=%h", test_name, expected, actual);
                fail_count = fail_count + 1;
            end
        end
    endtask

    initial begin
        test_count = 0;
        pass_count = 0;
        fail_count = 0;

        idu_lsu_rf_pipe3_inst_fof = 1'b0;
        idu_lsu_rf_pipe3_gateclk_sel = 1'b0;
        idu_lsu_rf_pipe3_sel = 1'b0;
        idu_lsu_rf_pipe3_inst_vld = 1'b0;
        idu_lsu_rf_pipe3_inst_ldr = 1'b0;
        idu_lsu_rf_pipe3_inst_fls = 1'b0;
        idu_lsu_rf_pipe3_inst_size = 2'b10;
        idu_lsu_rf_pipe3_inst_type = 4'b0000;
        idu_lsu_rf_pipe3_offset = 32'b0;
        idu_lsu_rf_pipe3_src0 = 64'b0;
        idu_lsu_rf_pipe3_src1 = 64'b0;
        idu_lsu_rf_pipe3_iid = 5'b0;
        cp0_lsu_dcache_en = 1'b1;
        cp0_yy_clk_en = 1'b1;

        @(posedge rst_b);
        repeat(5) @(posedge clk);

        $display("========================================");
        $display("FOF Load RTL Test Suite for RVV 1.0");
        $display("========================================");

        //----------------------------------------------------------------
        // Test Group 1: Basic FOF Signal Propagation
        //----------------------------------------------------------------
        $display("\n========== Basic FOF Signal Tests ==========");

        // FOF_001: FOF signal propagation
        $display("\n[FOF_001] FOF signal propagation");
        begin
            send_load_inst(1'b1, 32'h0, 64'h1000);
            check_result(ld_ag_dc_inst_fof, 1'b1, "FOF_001: FOF signal propagated");
            check_result(ld_ag_dc_inst_vld, 1'b1, "FOF_001: Inst valid");
        end

        // FOF_002: Non-FOF load
        $display("\n[FOF_002] Non-FOF load");
        begin
            send_load_inst(1'b0, 32'h0, 64'h2000);
            check_result(ld_ag_dc_inst_fof, 1'b0, "FOF_002: FOF signal not set");
            check_result(ld_ag_dc_inst_vld, 1'b1, "FOF_002: Inst valid");
        end

        //----------------------------------------------------------------
        // Test Group 2: Boundary Conditions
        //----------------------------------------------------------------
        $display("\n========== Boundary Condition Tests ==========");

        // BOUNDARY_001: FOF with zero address
        $display("\n[BOUNDARY_001] FOF with zero address");
        begin
            send_load_inst(1'b1, 32'h0, 64'h0);
            check_result(ld_ag_dc_inst_fof, 1'b1, "BOUNDARY_001: FOF with zero addr");
        end

        // BOUNDARY_002: FOF with max offset
        $display("\n[BOUNDARY_002] FOF with max offset");
        begin
            send_load_inst(1'b1, 32'hFFFFFFFF, 64'h1000);
            check_result(ld_ag_dc_inst_fof, 1'b1, "BOUNDARY_002: FOF with max offset");
        end

        // BOUNDARY_003: FOF with max base address
        $display("\n[BOUNDARY_003] FOF with max base address");
        begin
            send_load_inst(1'b1, 32'h0, 64'hFFFFFFFFFFFFFFFF);
            check_result(ld_ag_dc_inst_fof, 1'b1, "BOUNDARY_003: FOF with max base");
        end

        // BOUNDARY_004: Rapid FOF toggle
        $display("\n[BOUNDARY_004] Rapid FOF toggle");
        begin
            integer i;
            for (i = 0; i < 4; i = i + 1) begin
                send_load_inst(i[0], 32'h0, 64'h1000 + i);
                check_result(ld_ag_dc_inst_fof, i[0], $sformatf("BOUNDARY_004_%0d: FOF toggle", i));
            end
        end

        // BOUNDARY_005: Back-to-back FOF loads
        $display("\n[BOUNDARY_005] Back-to-back FOF loads");
        begin
            send_load_inst(1'b1, 32'h0, 64'h1000);
            check_result(ld_ag_dc_inst_fof, 1'b1, "BOUNDARY_005a: First FOF");
            send_load_inst(1'b1, 32'h4, 64'h1000);
            check_result(ld_ag_dc_inst_fof, 1'b1, "BOUNDARY_005b: Second FOF");
        end

        // BOUNDARY_006: FOF followed by non-FOF
        $display("\n[BOUNDARY_006] FOF followed by non-FOF");
        begin
            send_load_inst(1'b1, 32'h0, 64'h1000);
            check_result(ld_ag_dc_inst_fof, 1'b1, "BOUNDARY_006a: FOF load");
            send_load_inst(1'b0, 32'h0, 64'h2000);
            check_result(ld_ag_dc_inst_fof, 1'b0, "BOUNDARY_006b: Non-FOF load");
        end

        //----------------------------------------------------------------
        // Test Group 3: Signal Timing
        //----------------------------------------------------------------
        $display("\n========== Signal Timing Tests ==========");

        // TIMING_001: FOF signal timing check
        $display("\n[TIMING_001] FOF signal timing");
        begin
            @(posedge clk);
            idu_lsu_rf_pipe3_inst_fof <= 1'b1;
            idu_lsu_rf_pipe3_gateclk_sel <= 1'b1;
            idu_lsu_rf_pipe3_sel <= 1'b1;
            @(posedge clk);
            check_result(ld_ag_dc_inst_fof, 1'b1, "TIMING_001: FOF captured on next cycle");
            @(posedge clk);
            idu_lsu_rf_pipe3_gateclk_sel <= 1'b0;
            idu_lsu_rf_pipe3_sel <= 1'b0;
            repeat(2) @(posedge clk);
        end

        // TIMING_002: FOF signal hold check
        $display("\n[TIMING_002] FOF signal hold");
        begin
            send_load_inst(1'b1, 32'h0, 64'h1000);
            check_result(ld_ag_dc_inst_fof, 1'b1, "TIMING_002a: FOF after load");
            repeat(3) @(posedge clk);
            check_result(ld_ag_dc_inst_vld, 1'b0, "TIMING_002b: Valid cleared after no input");
        end

        //----------------------------------------------------------------
        // Test Group 4: Instruction Encoding Tests
        //----------------------------------------------------------------
        $display("\n========== Instruction Encoding Tests ==========");

        // ENCODING_001: vleff.v v0, (x1) encoding
        $display("\n[ENCODING_001] vleff.v v0, (x1) encoding");
        begin
            reg [31:0] inst;
            inst = 32'h02002007;
            $display("  Instruction encoding: 0x%h", inst);
            $display("  Opcode: 0x%h", inst[6:0]);
            $display("  funct3: 0x%h", inst[14:12]);
            $display("  rs1:    0x%h", inst[19:15]);
            $display("  vd:     0x%h", inst[11:7]);
            check_result(inst[6:0], 7'b0000111, "ENCODING_001: opcode correct");
            check_result(inst[14:12], 3'b000, "ENCODING_001: funct3 correct");
            check_result(inst[19:15], 5'd1, "ENCODING_001: rs1=x1");
            check_result(inst[11:7], 5'd0, "ENCODING_001: vd=v0");
        end

        // ENCODING_002: vleff.v v1, (x2) encoding
        $display("\n[ENCODING_002] vleff.v v1, (x2) encoding");
        begin
            reg [31:0] inst;
            inst = 32'h04002107;
            check_result(inst[19:15], 5'd2, "ENCODING_002: rs1=x2");
            check_result(inst[11:7], 5'd1, "ENCODING_002: vd=v1");
        end

        $display("\n========================================");
        $display("Test Summary");
        $display("========================================");
        $display("Total Tests: %d", test_count);
        $display("Passed:      %d", pass_count);
        $display("Failed:      %d", fail_count);
        $display("========================================");

        if (fail_count == 0)
            $display("ALL TESTS PASSED!");
        else
            $display("SOME TESTS FAILED!");

        #100;
        $finish;
    end

    initial begin
        #20000;
        $display("ERROR: Simulation timeout!");
        $finish;
    end

    initial begin
        $dumpfile("tb_lsu_fof_rtl.vcd");
        $dumpvars(0, tb_lsu_fof_rtl);
    end

endmodule

verification/tb_lsu_fof_rtl.vcd
$date
	Fri Apr 03 23:39:49 2026
$end
$version
	Icarus Verilog
$end
$timescale
	1s
$end
$scope module tb_lsu_fof_rtl $end
$var wire 1 ! ld_ag_dc_inst_fof $end
$var wire 1 " ld_ag_dc_inst_vld $end
$var wire 1 # ld_ag_dc_load_inst_vld $end
$var reg 1 $ clk $end
$var reg 1 % cp0_lsu_dcache_en $end
$var reg 1 & cp0_yy_clk_en $end
$var reg 1 ' idu_lsu_rf_pipe3_gateclk_sel $end
$var reg 5 ( idu_lsu_rf_pipe3_iid [4:0] $end
$var reg 1 ) idu_lsu_rf_pipe3_inst_fls $end
$var reg 1 * idu_lsu_rf_pipe3_inst_fof $end
$var reg 1 + idu_lsu_rf_pipe3_inst_ldr $end
$var reg 2 , idu_lsu_rf_pipe3_inst_size [1:0] $end
$var reg 4 - idu_lsu_rf_pipe3_inst_type [3:0] $end
$var reg 1 . idu_lsu_rf_pipe3_inst_vld $end
$var reg 32 / idu_lsu_rf_pipe3_offset [31:0] $end
$var reg 1 0 idu_lsu_rf_pipe3_sel $end
$var reg 64 1 idu_lsu_rf_pipe3_src0 [63:0] $end
$var reg 64 2 idu_lsu_rf_pipe3_src1 [63:0] $end
$var reg 1 3 ld_ag_inst_fof_reg $end
$var reg 1 4 ld_ag_inst_vld_reg $end
$var reg 1 5 rst_b $end
$var integer 32 6 fail_count [31:0] $end
$var integer 32 7 pass_count [31:0] $end
$var integer 32 8 test_count [31:0] $end
$scope begin $unm_blk_18 $end
$var integer 32 9 i [31:0] $end
$upscope $end
$scope begin $unm_blk_24 $end
$var reg 32 : inst [31:0] $end
$upscope $end
$scope begin $unm_blk_25 $end
$var reg 32 ; inst [31:0] $end
$upscope $end
$scope task check_result $end
$var reg 1 < actual $end
$var reg 1 = expected $end
$upscope $end
$scope task send_load_inst $end
$var reg 64 > base_addr [63:0] $end
$var reg 1 ? is_fof $end
$var reg 32 @ offset [31:0] $end
$upscope $end
$upscope $end
$enddefinitions $end
$comment Show the parameter values. $end
$dumpall
$end
#0
$dumpvars
bx @
x?
bx >
x=
x<
bx ;
bx :
bx 9
b0 8
b0 7
b0 6
05
x4
x3
b0 2
b0 1
00
b0 /
0.
b0 -
b10 ,
0+
0*
0)
b0 (
0'
1&
1%
0$
x#
x"
x!
$end
#5
0#
0"
04
0!
03
1$
#10
0$
#15
1$
#20
0$
15
#25
1$
#30
0$
#35
1$
#40
0$
#45
1$
#50
0$
#55
1$
#60
0$
#65
b1000000000000 >
b0 @
1?
1$
#70
0$
#75
1)
1+
1.
10
1'
b1000000000000 1
1*
1$
#80
0$
#85
1#
1"
14
1!
13
0.
00
0'
1$
#90
0$
#95
0#
0"
04
1$
#100
0$
#105
b10000000000000 >
0?
b1 6
b1 7
b10 8
1=
0<
1$
#110
0$
#115
1.
10
1'
b10000000000000 1
0*
1$
#120
0$
#125
1#
1"
14
0!
03
0.
00
0'
1$
#130
0$
#135
0#
0"
04
1$
#140
0$
#145
b0 >
1?
b10 6
b10 7
b100 8
1=
1$
#150
0$
#155
1.
10
1'
b0 1
1*
1$
#160
0$
#165
1#
1"
14
1!
13
0.
00
0'
1$
#170
0$
#175
0#
0"
04
1$
#180
0$
#185
b1000000000000 >
b11111111111111111111111111111111 @
b11 7
b101 8
1<
1$
#190
0$
#195
1.
10
1'
b1000000000000 1
b11111111111111111111111111111111 /
1$
#200
0$
#205
1#
1"
14
0.
00
0'
1$
#210
0$
#215
0#
0"
04
1$
#220
0$
#225
b1111111111111111111111111111111111111111111111111111111111111111 >
b0 @
b100 7
b110 8
1$
#230
0$
#235
1.
10
1'
b1111111111111111111111111111111111111111111111111111111111111111 1
b0 /
1$
#240
0$
#245
1#
1"
14
0.
00
0'
1$
#250
0$
#255
0#
0"
04
1$
#260
0$
#265
b1000000000000 >
0?
b0 9
b101 7
b111 8
1$
#270
0$
#275
1.
10
1'
b1000000000000 1
0*
1$
#280
0$
#285
1#
1"
14
0!
03
0.
00
0'
1$
#290
0$
#295
0#
0"
04
1$
#300
0$
#305
b1000000000001 >
1?
b1 9
b110 7
b1000 8
0=
0<
1$
#310
0$
#315
1.
10
1'
b1000000000001 1
1*
1$
#320
0$
#325
1#
1"
14
1!
13
0.
00
0'
1$
#330
0$
#335
0#
0"
04
1$
#340
0$
#345
b1000000000010 >
0?
b10 9
b111 7
b1001 8
1=
1<
1$
#350
0$
#355
1.
10
1'
b1000000000010 1
0*
1$
#360
0$
#365
1#
1"
14
0!
03
0.
00
0'
1$
#370
0$
#375
0#
0"
04
1$
#380
0$
#385
b1000000000011 >
1?
b11 9
b1000 7
b1010 8
0=
0<
1$
#390
0$
#395
1.
10
1'
b1000000000011 1
1*
1$
#400
0$
#405
1#
1"
14
1!
13
0.
00
0'
1$
#410
0$
#415
0#
0"
04
1$
#420
0$
#425
b1000000000000 >
b100 9
b1001 7
b1011 8
1=
1<
1$
#430
0$
#435
1.
10
1'
b1000000000000 1
1$
#440
0$
#445
1#
1"
14
0.
00
0'
1$
#450
0$
#455
0#
0"
04
1$
#460
0$
#465
b100 @
b1010 7
b1100 8
1$
#470
0$
#475
1.
10
1'
b100 /
1$
#480
0$
#485
1#
1"
14
0.
00
0'
1$
#490
0$
#495
0#
0"
04
1$
#500
0$
#505
b0 @
b1011 7
b1101 8
1$
#510
0$
#515
1.
10
1'
b0 /
1$
#520
0$
#525
1#
1"
14
0.
00
0'
1$
#530
0$
#535
0#
0"
04
1$
#540
0$
#545
b10000000000000 >
0?
b1100 7
b1110 8
1$
#550
0$
#555
1.
10
1'
b10000000000000 1
0*
1$
#560
0$
#565
1#
1"
14
0!
03
0.
00
0'
1$
#570
0$
#575
0#
0"
04
1$
#580
0$
#585
b1101 7
b1111 8
0=
0<
1$
#590
0$
#595
10
1'
1*
1$
#600
0$
#605
1#
1"
14
1!
13
b11 6
b10000 8
1=
1$
#610
0$
#615
00
0'
1$
#620
0$
#625
0#
0"
04
1$
#630
0$
#635
b1000000000000 >
1?
1$
#640
0$
#645
1.
10
1'
b1000000000000 1
1$
#650
0$
#655
1#
1"
14
0.
00
0'
1$
#660
0$
#665
0#
0"
04
1$
#670
0$
#675
b1110 7
b10001 8
1<
1$
#680
0$
#685
1$
#690
0$
#695
1$
#700
0$
#705
b100000000000010000100000111 ;
b101 6
b10000000000010000000000111 :
b10011 7
b11000 8
1=
0<
1$
