verification/tb/lsu/tb_lsu_fof.v
/*Copyright 2019-2021 T-Head Semiconductor Co., Ltd.

Licensed under the Apache License, Version 2.0 (the "License");
you may not use this file except in compliance with the License.
You may obtain a copy of the License at

    http://www.apache.org/licenses/LICENSE-2.0

Unless required by applicable law or agreed to in writing, software
distributed under the License is distributed on an "AS IS" BASIS,
WITHOUT WARRANTIES OR CONDITIONS OF ANY KIND, either express or implied.
See the License for the specific language governing permissions and
limitations under the License.
*/

// FOF (Fault-Only-First) Load Testbench for RVV 1.0
// Created: 2026-04-02
// Description: Test FOF load signal propagation through pipeline stages

module tb_lsu_fof;

    // Clock and Reset
    reg clk;
    reg rst_b;

    // IDU -> RF signals
    reg         idu_lsu_rf_pipe3_inst_vld;
    reg         idu_lsu_rf_pipe3_inst_fof;
    reg  [6:0]  idu_lsu_rf_pipe3_iid;

    // LD_AG stage signals
    wire        ld_ag_inst_fof;
    wire        ld_ag_dc_inst_fof;

    // LD_DC stage signals
    wire        ld_dc_inst_fof;

    // LD_DA stage signals
    wire        ld_da_inst_fof;

    // Pipeline control
    reg         ag_stage_vld;
    reg         dc_stage_vld;
    reg         da_stage_vld;

    // Test counters
    integer test_count;
    integer pass_count;
    integer fail_count;

    // Clock generation - 100MHz
    initial begin
        clk = 0;
        forever #5 clk = ~clk;
    end

    // Reset generation
    initial begin
        rst_b = 0;
        #20 rst_b = 1;
    end

    // LD_AG Stage - FOF signal register
    reg ld_ag_inst_fof_reg;
    always @(posedge clk or negedge rst_b) begin
        if (!rst_b) begin
            ld_ag_inst_fof_reg <= 1'b0;
        end else if (idu_lsu_rf_pipe3_inst_vld) begin
            ld_ag_inst_fof_reg <= idu_lsu_rf_pipe3_inst_fof;
        end
    end
    assign ld_ag_inst_fof = ld_ag_inst_fof_reg;
    assign ld_ag_dc_inst_fof = ld_ag_inst_fof_reg;

    // LD_DC Stage - FOF signal register
    reg ld_dc_inst_fof_reg;
    always @(posedge clk or negedge rst_b) begin
        if (!rst_b) begin
            ld_dc_inst_fof_reg <= 1'b0;
        end else if (ag_stage_vld) begin
            ld_dc_inst_fof_reg <= ld_ag_dc_inst_fof;
        end
    end
    assign ld_dc_inst_fof = ld_dc_inst_fof_reg;

    // LD_DA Stage - FOF signal register
    reg ld_da_inst_fof_reg;
    always @(posedge clk or negedge rst_b) begin
        if (!rst_b) begin
            ld_da_inst_fof_reg <= 1'b0;
        end else if (dc_stage_vld) begin
            ld_da_inst_fof_reg <= ld_dc_inst_fof;
        end
    end
    assign ld_da_inst_fof = ld_da_inst_fof_reg;

    // Test Task: Send FOF instruction through pipeline
    task send_fof_inst;
        input fof_flag;
        begin
            @(posedge clk);
            idu_lsu_rf_pipe3_inst_vld <= 1'b1;
            idu_lsu_rf_pipe3_inst_fof <= fof_flag;
            idu_lsu_rf_pipe3_iid <= $random;
            
            // Advance through pipeline
            @(posedge clk);
            ag_stage_vld <= 1'b1;
            idu_lsu_rf_pipe3_inst_vld <= 1'b0;
            
            @(posedge clk);
            dc_stage_vld <= 1'b1;
            ag_stage_vld <= 1'b0;
            
            @(posedge clk);
            da_stage_vld <= 1'b1;
            dc_stage_vld <= 1'b0;
            
            @(posedge clk);
            da_stage_vld <= 1'b0;
        end
    endtask

    // Test Task: Check result
    task check_result;
        input        actual;
        input        expected;
        input string test_name;
        begin
            test_count = test_count + 1;
            if (actual === expected) begin
                $display("[PASS] %s: Expected=%b, Actual=%b", test_name, expected, actual);
                pass_count = pass_count + 1;
            end else begin
                $display("[FAIL] %s: Expected=%b, Actual=%b", test_name, expected, actual);
                fail_count = fail_count + 1;
            end
        end
    endtask

    // Main Test Sequence
    initial begin
        // Initialize
        test_count = 0;
        pass_count = 0;
        fail_count = 0;
        idu_lsu_rf_pipe3_inst_vld = 1'b0;
        idu_lsu_rf_pipe3_inst_fof = 1'b0;
        idu_lsu_rf_pipe3_iid = 7'b0;
        ag_stage_vld = 1'b0;
        dc_stage_vld = 1'b0;
        da_stage_vld = 1'b0;

        // Wait for reset
        @(posedge rst_b);
        @(posedge clk);

        $display("========================================");
        $display("FOF Load Test Suite for RVV 1.0");
        $display("========================================");

        //----------------------------------------------------------------
        // Test Case FOF_001: FOF Signal at IDU Stage
        //----------------------------------------------------------------
        $display("\n[FOF_001] FOF Signal at IDU Stage Test");
        begin
            @(posedge clk);
            idu_lsu_rf_pipe3_inst_vld <= 1'b1;
            idu_lsu_rf_pipe3_inst_fof <= 1'b1;
            @(posedge clk);
            check_result(idu_lsu_rf_pipe3_inst_fof, 1'b1, "FOF_001: IDU stage FOF signal");
            idu_lsu_rf_pipe3_inst_vld <= 1'b0;
        end

        //----------------------------------------------------------------
        // Test Case FOF_002: FOF Signal Propagation to LD_AG
        //----------------------------------------------------------------
        $display("\n[FOF_002] FOF Signal Propagation to LD_AG Test");
        begin
            send_fof_inst(1'b1);
            check_result(ld_ag_inst_fof, 1'b1, "FOF_002: LD_AG stage FOF signal");
        end

        //----------------------------------------------------------------
        // Test Case FOF_003: FOF Signal Propagation to LD_DC
        //----------------------------------------------------------------
        $display("\n[FOF_003] FOF Signal Propagation to LD_DC Test");
        begin
            send_fof_inst(1'b1);
            check_result(ld_dc_inst_fof, 1'b1, "FOF_003: LD_DC stage FOF signal");
        end

        //----------------------------------------------------------------
        // Test Case FOF_004: FOF Signal Propagation to LD_DA
        //----------------------------------------------------------------
        $display("\n[FOF_004] FOF Signal Propagation to LD_DA Test");
        begin
            send_fof_inst(1'b1);
            check_result(ld_da_inst_fof, 1'b1, "FOF_004: LD_DA stage FOF signal");
        end

        //----------------------------------------------------------------
        // Test Case FOF_005: Non-FOF Instruction
        //----------------------------------------------------------------
        $display("\n[FOF_005] Non-FOF Instruction Test");
        begin
            send_fof_inst(1'b0);
            check_result(ld_da_inst_fof, 1'b0, "FOF_005: Non-FOF instruction");
        end

        //----------------------------------------------------------------
        // Test Case FOF_006: FOF Signal Reset
        //----------------------------------------------------------------
        $display("\n[FOF_006] FOF Signal Reset Test");
        begin
            // Send FOF instruction
            send_fof_inst(1'b1);
            // Reset
            @(posedge clk);
            rst_b <= 1'b0;
            @(posedge clk);
            rst_b <= 1'b1;
            @(posedge clk);
            check_result(ld_ag_inst_fof, 1'b0, "FOF_006: FOF signal after reset");
        end

        //----------------------------------------------------------------
        // Test Case FOF_007: Multiple FOF Instructions
        //----------------------------------------------------------------
        $display("\n[FOF_007] Multiple FOF Instructions Test");
        begin
            // Send first FOF instruction
            send_fof_inst(1'b1);
            check_result(ld_da_inst_fof, 1'b1, "FOF_007a: First FOF instruction");

            // Send second FOF instruction
            send_fof_inst(1'b1);
            check_result(ld_da_inst_fof, 1'b1, "FOF_007b: Second FOF instruction");

            // Send non-FOF instruction
            send_fof_inst(1'b0);
            check_result(ld_da_inst_fof, 1'b0, "FOF_007c: Non-FOF instruction");
        end

        // Print Summary
        $display("\n========================================");
        $display("Test Summary");
        $display("========================================");
        $display("Total Tests: %d", test_count);
        $display("Passed:      %d", pass_count);
        $display("Failed:      %d", fail_count);
        $display("========================================");

        if (fail_count == 0)
            $display("ALL TESTS PASSED!");
        else
            $display("SOME TESTS FAILED!");

        #100;
        $finish;
    end

    // Timeout
    initial begin
        #10000;
        $display("ERROR: Simulation timeout!");
        $finish;
    end

    // Waveform dump
    initial begin
        $dumpfile("tb_lsu_fof.vcd");
        $dumpvars(0, tb_lsu_fof);
    end

endmodule

verification/tb_lsu_fof.vcd
$date
	Fri Apr 03 22:23:10 2026
$end
$version
	Icarus Verilog
$end
$timescale
	1s
$end
$scope module tb_lsu_fof $end
$var wire 1 ! ld_ag_dc_inst_fof $end
$var wire 1 " ld_ag_inst_fof $end
$var wire 1 # ld_da_inst_fof $end
$var wire 1 $ ld_dc_inst_fof $end
$var reg 1 % ag_stage_vld $end
$var reg 1 & clk $end
$var reg 1 ' da_stage_vld $end
$var reg 1 ( dc_stage_vld $end
$var reg 7 ) idu_lsu_rf_pipe3_iid [6:0] $end
$var reg 1 * idu_lsu_rf_pipe3_inst_fof $end
$var reg 1 + idu_lsu_rf_pipe3_inst_vld $end
$var reg 1 , ld_ag_inst_fof_reg $end
$var reg 1 - ld_da_inst_fof_reg $end
$var reg 1 . ld_dc_inst_fof_reg $end
$var reg 1 / rst_b $end
$var integer 32 0 fail_count [31:0] $end
$var integer 32 1 pass_count [31:0] $end
$var integer 32 2 test_count [31:0] $end
$scope task check_result $end
$var reg 1 3 actual $end
$var reg 1 4 expected $end
$upscope $end
$scope task send_fof_inst $end
$var reg 1 5 fof_flag $end
$upscope $end
$upscope $end
$enddefinitions $end
$comment Show the parameter values. $end
$dumpall
$end
#0
$dumpvars
x5
x4
x3
b0 2
b0 1
b0 0
0/
x.
x-
x,
0+
0*
b0 )
0(
0'
0&
0%
x$
x#
x"
x!
$end
#5
0!
0"
0,
0$
0.
0#
0-
1&
#10
0&
#15
1&
#20
0&
1/
#25
1&
#30
0&
#35
1*
1+
1&
#40
0&
#45
1!
1"
1,
0+
15
b1 1
b1 2
14
13
1&
#50
0&
#55
b100100 )
1+
1&
#60
0&
#65
0+
1%
1&
#70
0&
#75
1$
1.
0%
1(
1&
#80
0&
#85
1#
1-
0(
1'
1&
#90
0&
#95
0'
b10 1
b10 2
1&
#100
0&
#105
b1 )
1+
1&
#110
0&
#115
0+
1%
1&
#120
0&
#125
0%
1(
1&
#130
0&
#135
0(
1'
1&
#140
0&
#145
0'
b11 1
b11 2
1&
#150
0&
#155
b1001 )
1+
1&
#160
0&
#165
0+
1%
1&
#170
0&
#175
0%
1(
1&
#180
0&
#185
0(
1'
1&
#190
0&
#195
0'
05
b100 1
b100 2
1&
#200
0&
#205
b1100011 )
0*
1+
1&
#210
0&
#215
0!
0"
0,
0+
1%
1&
#220
0&
#225
0$
0.
0%
1(
1&
#230
0&
#235
0#
0-
0(
1'
1&
#240
0&
#245
0'
15
b101 1
b101 2
04
03
1&
#250
0&
#255
b1101 )
1*
1+
1&
#260
0&
#265
1!
1"
1,
0+
1%
1&
#270
0&
#275
1$
1.
0%
1(
1&
#280
0&
#285
1#
1-
0(
1'
1&
#290
0&
#295
0'
1&
#300
0&
#305
0#
0-
0$
0.
0!
0"
0,
0/
1&
#310
0&
#315
1/
1&
#320
0&
#325
b110 1
b110 2
1&
#330
0&
#335
1+
1&
#340
0&
#345
1!
1"
1,
0+
1%
1&
#350
0&
#355
1$
1.
0%
1(
1&
#360
0&
#365
1#
1-
0(
1'
1&
#370
0&
#375
0'
b111 1
b111 2
14
13
1&
#380
0&
#385
b1100101 )
1+
1&
#390
0&
#395
0+
1%
1&
#400
0&
#405
0%
1(
1&
#410
0&
#415
0(
1'
1&
#420
0&
#425
0'
05
b1000 1
b1000 2
1&
#430
0&
#435
b10010 )
0*
1+
1&
#440
0&
#445
0!
0"
0,
0+
1%
1&
#450
0&
#455
0$
0.
0%
1(
1&
#460
0&
#465
0#
0-
0(
1'
1&
#470
0&
#475
0'
b1001 1
b1001 2
04
03
1&
