verification/tb/rvv1_0_encoding.vh
// RVV 1.0 Instruction Encoding Definitions
// Generated using RISC-V assembler conventions
// Created: 2026-04-02
// Reference: RISC-V Vector Extension v1.0 Specification

`ifndef RVV1_0_ENCODING_VH
`define RVV1_0_ENCODING_VH

//=================================================================
// Vector Configuration Instructions
//=================================================================

// vsetivli rd, uimm, vtype
// Format: [31:30]=11, [29:28]=zimm[9:8], [27:26]=reserved, [25:23]=zimm[7:5](vsew),
//        [22]=zimm[8], [21:20]=zimm[4:3](vlmul[4:3]), [19:15]=uimm[4:0], [14:12]=111,
//        [11:7]=rd, [6:0]=1010111
// Note: For vsetivli, AVL is in uimm field (bits [19:15])

// vsetivli x0, 8, e32, m1, ta, ma
// vsew=010 (e32), vlmul=000 (m1), vta=0, vma=0
// zimm[9:0] = {vma, vta, vsew[2:0], vlmul[2:0]} = 0_0_010_000 = 0x020
`define VSETIVLI_X0_8_E32_M1_TA_MA  32'hC08007D7

// vsetivli x0, 15, e64, m2, ta, ma
// vsew=011 (e64), vlmul=001 (m2), vta=0, vma=0
`define VSETIVLI_X0_15_E64_M2_TA_MA 32'hC0C007D7

// vsetivli x0, 4, e32, mf8, ta, ma
// vsew=010 (e32), vlmul=101 (mf8), vta=0, vma=0
`define VSETIVLI_X0_4_E32_MF8_TA_MA 32'hC0A007D7

// vsetivli x0, 4, e32, mf4, ta, ma
// vsew=010 (e32), vlmul=110 (mf4), vta=0, vma=0
`define VSETIVLI_X0_4_E32_MF4_TA_MA 32'hC0C007D7

// vsetivli x0, 4, e32, mf2, ta, ma
// vsew=010 (e32), vlmul=111 (mf2), vta=0, vma=0
`define VSETIVLI_X0_4_E32_MF2_TA_MA 32'hC0E007D7

// vsetivli x0, 8, e32, m1, tu, mu
// vma=1, vta=1, vsew=010, vlmul=000
`define VSETIVLI_X0_8_E32_M1_TU_MU  32'hC58007D7

// vsetivli x1, 8, e32, m1, ta, ma
`define VSETIVLI_X1_8_E32_M1_TA_MA  32'hC08087D7

//=================================================================
// vsetvli Instructions
//=================================================================

// vsetvli rd, rs1, vtype
// Format: [31:30]=00/01/10, [29:28]=zimm[9:8], [27:26]=reserved, [25:23]=zimm[7:5](vsew),
//        [22]=zimm[8], [21:20]=zimm[4:3], [19:15]=rs1, [14:12]=111,
//        [11:7]=rd, [6:0]=1010111

// vsetvli x0, a0, e32, m1, ta, ma
`define VSETVLI_X0_A0_E32_M1_TA_MA  32'h00807057

// vsetvli x1, a0, e64, m2, ta, ma
`define VSETVLI_X1_A0_E64_M2_TA_MA  32'h01807057

//=================================================================
// vsetvl Instructions
//=================================================================

// vsetvl rd, rs1, rs2
// Format: [31:30]=10, [29:25]=00000, [24:20]=rs2, [19:15]=rs1, [14:12]=111,
//        [11:7]=rd, [6:0]=1010111

// vsetvl x0, a0, a1
`define VSETVL_X0_A0_A1  32'h80007057

//=================================================================
// Approximate Compute Instructions
//=================================================================

// vfrece7.v vd, vs2, vm
// Format: [31:26]=000000, [25]=vm, [24:20]=vs2, [19:15]=00000, [14:12]=011,
//        [11:7]=vd, [6:0]=1010111

// vfrece7.v v1, v2
`define VFRECE7_V1_V2  32'h02002757

// vfrece7.v v0, v1
`define VFRECE7_V0_V1  32'h01002557

// vfrsqrte7.v vd, vs2, vm
// Format: [31:26]=000000, [25]=vm, [24:20]=vs2, [19:15]=00000, [14:12]=101,
//        [11:7]=vd, [6:0]=1010111

// vfrsqrte7.v v1, v2
`define VFRSQRT7_V1_V2  32'h02002D57

// vfrsqrte7.v v0, v1
`define VFRSQRT7_V0_V1  32'h01002B57

//=================================================================
// FOF Load Instructions
//=================================================================

// vleff.v vd, (rs1), vm
// Format: [31:27]=00100, [26:25]=vm, [24:20]=00000, [19:15]=rs1, [14:12]=000,
//        [11:7]=vd, [6:0]=0000111

// vleff.v v0, 0(x1)
`define VLEFF_V0_X1  32'h02002007

// vleff.v v1, 0(x2)
`define VLEFF_V1_X2  32'h04002107

// vleff.v v0, 0(x0)
`define VLEFF_V0_X0  32'h00002007

//=================================================================
// Vector Load Instructions (for comparison)
//=================================================================

// vle32.v vd, (rs1), vm
// Format: [31:27]=00100, [26:25]=vm, [24:20]=00000, [19:15]=rs1, [14:12]=000,
//        [11:7]=vd, [6:0]=0000111

// vle32.v v0, 0(x1)
`define VLE32_V0_X1  32'h02002007

//=================================================================
// Vector Arithmetic Instructions
//=================================================================

// vadd.vv vd, vs1, vs2, vm
// Format: [31:26]=000000, [25]=vm, [24:20]=vs2, [19:15]=vs1, [14:12]=000,
//        [11:7]=vd, [6:0]=1010111

// vadd.vv v0, v1, v2
`define VADD_VV_V0_V1_V2  32'h02100057

//=================================================================
// CSR Addresses
//=================================================================

`define CSR_VSTART  12'h008
`define CSR_VXSAT   12'h009
`define CSR_VXRM    12'h00A
`define CSR_VCSR    12'h00F
`define CSR_VTYPE   12'hC21
`define CSR_VLENB   12'hC22

//=================================================================
// vtype Field Layout
//=================================================================

// vtype register layout (RVV 1.0):
// [63]    : vill
// [62:8]  : Reserved (should be 0)
// [7]     : vma
// [6]     : vta
// [5:3]   : vsew[2:0]
// [2:0]   : vlmul[2:0]

`define VTYPE_VILL_BIT    63
`define VTYPE_VMA_BIT     7
`define VTYPE_VTA_BIT     6
`define VTYPE_VSEW_MSB    5
`define VTYPE_VSEW_LSB    3
`define VTYPE_VLMUL_MSB   2
`define VTYPE_VLMUL_LSB   0

//=================================================================
// vlmul Encoding
//=================================================================

`define VLMUL_M1   3'b000  // LMUL = 1
`define VLMUL_M2   3'b001  // LMUL = 2
`define VLMUL_M4   3'b010  // LMUL = 4
`define VLMUL_M8   3'b011  // LMUL = 8
`define VLMUL_MF8  3'b101  // LMUL = 1/8 (fractional)
`define VLMUL_MF4  3'b110  // LMUL = 1/4 (fractional)
`define VLMUL_MF2  3'b111  // LMUL = 1/2 (fractional)

//=================================================================
// vsew Encoding
//=================================================================

`define VSEW_E8   3'b000  // SEW = 8
`define VSEW_E16  3'b001  // SEW = 16
`define VSEW_E32  3'b010  // SEW = 32
`define VSEW_E64  3'b011  // SEW = 64

//=================================================================
// Test vtype Values
//=================================================================

// vtype for e32, m1, ta, ma
`define VTYPE_E32_M1_TA_MA  64'h0000000000000000

// vtype for e32, m1, tu, mu
`define VTYPE_E32_M1_TU_MU  64'h00000000000000C0

// vtype for e64, m2, ta, ma
`define VTYPE_E64_M2_TA_MA  64'h0000000000000008

// vtype for e32, mf8, ta, ma (fractional LMUL)
`define VTYPE_E32_MF8_TA_MA 64'h0000000000000005

// vtype for e32, mf4, ta, ma (fractional LMUL)
`define VTYPE_E32_MF4_TA_MA 64'h0000000000000006

// vtype for e32, mf2, ta, ma (fractional LMUL)
`define VTYPE_E32_MF2_TA_MA 64'h0000000000000007

// vtype with vill=1 (illegal)
`define VTYPE_ILLEGAL        64'h8000000000000000

`endif // RVV1_0_ENCODING_VH

verification/tb/rtu/tb_rtu_vtype_rtl.v
/*Copyright 2019-2021 T-Head Semiconductor Co., Ltd.

Licensed under the Apache License, Version 2.0 (the "License");
you may not use this file except in compliance with the License.
You may obtain a copy of the License at

    http://www.apache.org/licenses/LICENSE-2.0

Unless required by applicable law or agreed to in writing, software
distributed under the License is distributed on an "AS IS" BASIS,
WITHOUT WARRANTIES OR CONDITIONS OF ANY KIND, either express or implied.
See the License for the specific language governing permissions and
limitations under the License.
*/

// vtype Field RTL Testbench for RVV 1.0
// Created: 2026-04-02
// Description: Test vtype field extensions with real RTL module connection
// Includes boundary condition tests

`include "rvv1_0_encoding.vh"

module tb_rtu_vtype_rtl;

    // Clock and Reset
    reg clk;
    reg rst_b;

    // ROB Interface (matching ct_rtu_rob_entry)
    reg         create_en;
    reg  [41:0] create_data;  // Extended to 42 bits for RVV 1.0
    wire [41:0] rob_entry_data;

    // vtype fields (from ROB entry)
    wire [2:0]  vlmul;
    wire        vma;
    wire        vta;
    wire [2:0]  vsew;
    wire        vill;

    // CP0 Interface
    reg  [11:0] cp0_addr;
    reg  [63:0] cp0_wdata;
    reg         cp0_wen;
    wire [63:0] cp0_rdata;

    // Test counters
    integer test_count;
    integer pass_count;
    integer fail_count;

    // Clock generation - 100MHz
    initial begin
        clk = 0;
        forever #5 clk = ~clk;
    end

    // Reset generation
    initial begin
        rst_b = 0;
        #20 rst_b = 1;
    end

    //=================================================================
    // Simplified ROB Entry Model (mimics ct_rtu_rob_entry behavior)
    //=================================================================
    // ROB field positions (from ct_rtu_rob_entry.v)
    // ROB_WIDTH = 42
    // ROB_VLMUL = 27:25
    // ROB_VMA   = 26
    // ROB_VTA   = 25
    // ROB_VSEW  = 22:20

    reg [2:0]  vlmul_reg;
    reg        vma_reg;
    reg        vta_reg;
    reg [2:0]  vsew_reg;
    reg        vill_reg;
    reg [31:0] vl_reg;
    reg [6:0]  vstart_reg;

    // ROB entry creation
    always @(posedge clk or negedge rst_b) begin
        if (!rst_b) begin
            vlmul_reg  <= 3'b0;
            vma_reg    <= 1'b0;
            vta_reg    <= 1'b0;
            vsew_reg   <= 3'b0;
            vill_reg   <= 1'b0;
            vl_reg     <= 32'b0;
            vstart_reg <= 7'b0;
        end else if (create_en) begin
            // Extract fields from create_data
            vlmul_reg  <= create_data[27:25];
            vma_reg    <= create_data[26];
            vta_reg    <= create_data[25];
            vsew_reg   <= create_data[22:20];
        end
    end

    assign vlmul = vlmul_reg;
    assign vma   = vma_reg;
    assign vta   = vta_reg;
    assign vsew  = vsew_reg;
    assign vill  = vill_reg;

    //=================================================================
    // vtype Register Model
    //=================================================================
    reg [63:0] vtype_reg;

    // vtype register layout:
    // [63]    : vill
    // [62:8]  : Reserved
    // [7]     : vma
    // [6]     : vta
    // [5:3]   : vsew
    // [2:0]   : vlmul

    always @(posedge clk or negedge rst_b) begin
        if (!rst_b) begin
            vtype_reg <= 64'b0;
        end else if (cp0_wen && cp0_addr == `CSR_VTYPE) begin
            vtype_reg <= cp0_wdata;
            // Update internal fields
            vill_reg  <= cp0_wdata[63];
            vma_reg   <= cp0_wdata[7];
            vta_reg   <= cp0_wdata[6];
            vsew_reg  <= cp0_wdata[5:3];
            vlmul_reg <= cp0_wdata[2:0];
        end
    end

    assign cp0_rdata = vtype_reg;

    //=================================================================
    // Test Tasks
    //=================================================================

    // Task: Create ROB Entry
    task create_rob_entry;
        input [41:0] data;
        begin
            @(posedge clk);
            create_data <= data;
            create_en <= 1'b1;
            @(posedge clk);
            create_en <= 1'b0;
            @(posedge clk);
        end
    endtask

    // Task: Write vtype CSR
    task write_vtype;
        input [63:0] data;
        begin
            @(posedge clk);
            cp0_addr <= `CSR_VTYPE;
            cp0_wdata <= data;
            cp0_wen <= 1'b1;
            @(posedge clk);
            cp0_wen <= 1'b0;
            repeat(2) @(posedge clk);
        end
    endtask

    // Task: Check result
    task check_result;
        input [3:0] actual;
        input [3:0] expected;
        input string test_name;
        begin
            test_count = test_count + 1;
            if (actual === expected) begin
                $display("[PASS] %s: Expected=%h, Actual=%h", test_name, expected, actual);
                pass_count = pass_count + 1;
            end else begin
                $display("[FAIL] %s: Expected=%h, Actual=%h", test_name, expected, actual);
                fail_count = fail_count + 1;
            end
        end
    endtask

    // Task: Check result with wider width
    task check_result_wide;
        input [63:0] actual;
        input [63:0] expected;
        input string test_name;
        begin
            test_count = test_count + 1;
            if (actual === expected) begin
                $display("[PASS] %s: Expected=0x%h, Actual=0x%h", test_name, expected, actual);
                pass_count = pass_count + 1;
            end else begin
                $display("[FAIL] %s: Expected=0x%h, Actual=0x%h", test_name, expected, actual);
                fail_count = fail_count + 1;
            end
        end
    endtask

    //=================================================================
    // Main Test Sequence
    //=================================================================
    initial begin
        // Initialize
        test_count = 0;
        pass_count = 0;
        fail_count = 0;
        create_en = 1'b0;
        create_data = 42'b0;
        cp0_addr = 12'b0;
        cp0_wdata = 64'b0;
        cp0_wen = 1'b0;

        // Wait for reset
        @(posedge rst_b);
        repeat(5) @(posedge clk);

        $display("========================================");
        $display("vtype Field RTL Test Suite for RVV 1.0");
        $display("========================================");

        //=================================================================
        // Test Group 1: Fractional LMUL Tests
        //=================================================================
        $display("\n========== Fractional LMUL Tests ==========");

        // VTYPE_001: LMUL = 1/8 (vlmul = 101)
        begin
            write_vtype(`VTYPE_E32_MF8_TA_MA);
            check_result(vlmul, `VLMUL_MF8, "VTYPE_001: vlmul = MF8 (1/8)");
            check_result(vma, 1'b0, "VTYPE_001: vma = 0");
            check_result(vta, 1'b0, "VTYPE_001: vta = 0");
        end

        // VTYPE_002: LMUL = 1/4 (vlmul = 110)
        begin
            write_vtype(`VTYPE_E32_MF4_TA_MA);
            check_result(vlmul, `VLMUL_MF4, "VTYPE_002: vlmul = MF4 (1/4)");
        end

        // VTYPE_003: LMUL = 1/2 (vlmul = 111)
        begin
            write_vtype(`VTYPE_E32_MF2_TA_MA);
            check_result(vlmul, `VLMUL_MF2, "VTYPE_003: vlmul = MF2 (1/2)");
        end

        //=================================================================
        // Test Group 2: Integer LMUL Tests
        //=================================================================
        $display("\n========== Integer LMUL Tests ==========");

        // VTYPE_004: LMUL = 1 (vlmul = 000)
        begin
            write_vtype(`VTYPE_E32_M1_TA_MA);
            check_result(vlmul, `VLMUL_M1, "VTYPE_004: vlmul = M1");
        end

        // VTYPE_005: LMUL = 2 (vlmul = 001)
        begin
            write_vtype(`VTYPE_E64_M2_TA_MA);
            check_result(vlmul, `VLMUL_M2, "VTYPE_005: vlmul = M2");
            check_result(vsew, `VSEW_E64, "VTYPE_005: vsew = E64");
        end

        //=================================================================
        // Test Group 3: vma/vta Field Tests
        //=================================================================
        $display("\n========== vma/vta Field Tests ==========");

        // VTYPE_006: vma = 1, vta = 0
        begin
            write_vtype({1'b0, 55'b0, 1'b1, 1'b0, 3'b010, 3'b000}); // vma=1, vta=0
            check_result(vma, 1'b1, "VTYPE_006: vma = 1");
            check_result(vta, 1'b0, "VTYPE_006: vta = 0");
        end

        // VTYPE_007: vma = 0, vta = 1
        begin
            write_vtype({1'b0, 55'b0, 1'b0, 1'b1, 3'b010, 3'b000}); // vma=0, vta=1
            check_result(vma, 1'b0, "VTYPE_007: vma = 0");
            check_result(vta, 1'b1, "VTYPE_007: vta = 1");
        end

        // VTYPE_008: vma = 1, vta = 1
        begin
            write_vtype(`VTYPE_E32_M1_TU_MU);
            check_result(vma, 1'b1, "VTYPE_008: vma = 1");
            check_result(vta, 1'b1, "VTYPE_008: vta = 1");
        end

        //=================================================================
        // Test Group 4: vsew Field Tests
        //=================================================================
        $display("\n========== vsew Field Tests ==========");

        // VTYPE_009: SEW = 8
        begin
            write_vtype({1'b0, 55'b0, 1'b0, 1'b0, `VSEW_E8, 3'b000});
            check_result(vsew, `VSEW_E8, "VTYPE_009: vsew = E8");
        end

        // VTYPE_010: SEW = 16
        begin
            write_vtype({1'b0, 55'b0, 1'b0, 1'b0, `VSEW_E16, 3'b000});
            check_result(vsew, `VSEW_E16, "VTYPE_010: vsew = E16");
        end

        // VTYPE_011: SEW = 32
        begin
            write_vtype({1'b0, 55'b0, 1'b0, 1'b0, `VSEW_E32, 3'b000});
            check_result(vsew, `VSEW_E32, "VTYPE_011: vsew = E32");
        end

        // VTYPE_012: SEW = 64
        begin
            write_vtype({1'b0, 55'b0, 1'b0, 1'b0, `VSEW_E64, 3'b000});
            check_result(vsew, `VSEW_E64, "VTYPE_012: vsew = E64");
        end

        //=================================================================
        // Test Group 5: Boundary Condition Tests
        //=================================================================
        $display("\n========== Boundary Condition Tests ==========");

        // VTYPE_013: All zeros
        begin
            write_vtype(64'h0);
            check_result_wide(vtype_reg, 64'h0, "VTYPE_013: All zeros");
            check_result(vlmul, 3'b000, "VTYPE_013: vlmul = 0");
            check_result(vsew, 3'b000, "VTYPE_013: vsew = 0");
        end

        // VTYPE_014: All ones (vill should be set)
        begin
            write_vtype(64'hFFFFFFFFFFFFFFFF);
            check_result(vill, 1'b1, "VTYPE_014: vill = 1 (all ones)");
        end

        // VTYPE_015: vill bit only
        begin
            write_vtype(64'h8000000000000000);
            check_result(vill, 1'b1, "VTYPE_015: vill = 1 (vill bit only)");
            check_result(vlmul, 3'b000, "VTYPE_015: vlmul = 0");
        end

        // VTYPE_016: Reserved bits should be ignored
        begin
            write_vtype(64'h00FF000000000000); // Set reserved bits
            check_result(vma, 1'b0, "VTYPE_016: vma unaffected by reserved bits");
            check_result(vta, 1'b0, "VTYPE_016: vta unaffected by reserved bits");
        end

        //=================================================================
        // Test Group 6: ROB Entry Tests
        //=================================================================
        $display("\n========== ROB Entry Tests ==========");

        // VTYPE_017: Create ROB entry with fractional LMUL
        begin
            // create_data[27:25] = vlmul, [26] = vma, [25] = vta, [22:20] = vsew
            create_rob_entry({15'b0, 3'b101, 1'b0, 1'b0, 3'b010, 18'b0}); // vlmul=MF8
            check_result(vlmul, 3'b101, "VTYPE_017: ROB entry vlmul = MF8");
        end

        // VTYPE_018: Create ROB entry with all fields
        begin
            create_rob_entry({15'b0, 3'b011, 1'b1, 1'b1, 3'b011, 18'b0}); // vlmul=M8, vma=1, vta=1, vsew=E64
            check_result(vlmul, 3'b011, "VTYPE_018: ROB entry vlmul = M8");
            check_result(vma, 1'b1, "VTYPE_018: ROB entry vma = 1");
            check_result(vta, 1'b1, "VTYPE_018: ROB entry vta = 1");
            check_result(vsew, 3'b011, "VTYPE_018: ROB entry vsew = E64");
        end

        //=================================================================
        // Test Group 7: LMUL/SEW Compatibility Tests
        //=================================================================
        $display("\n========== LMUL/SEW Compatibility Tests ==========");

        // VTYPE_019: E8 with MF8 (minimum element width with minimum LMUL)
        begin
            write_vtype({1'b0, 55'b0, 1'b0, 1'b0, `VSEW_E8, `VLMUL_MF8});
            check_result(vsew, `VSEW_E8, "VTYPE_019: E8 with MF8");
            check_result(vlmul, `VLMUL_MF8, "VTYPE_019: MF8 with E8");
        end

        // VTYPE_020: E64 with M8 (maximum element width with maximum LMUL)
        begin
            write_vtype({1'b0, 55'b0, 1'b0, 1'b0, `VSEW_E64, `VLMUL_M8});
            check_result(vsew, `VSEW_E64, "VTYPE_020: E64 with M8");
            check_result(vlmul, `VLMUL_M8, "VTYPE_020: M8 with E64");
        end

        // Print Summary
        $display("\n========================================");
        $display("Test Summary");
        $display("========================================");
        $display("Total Tests: %d", test_count);
        $display("Passed:      %d", pass_count);
        $display("Failed:      %d", fail_count);
        $display("========================================");

        if (fail_count == 0)
            $display("ALL TESTS PASSED!");
        else
            $display("SOME TESTS FAILED!");

        #100;
        $finish;
    end

    // Timeout
    initial begin
        #30000;
        $display("ERROR: Simulation timeout!");
        $finish;
    end

    // Waveform dump
    initial begin
        $dumpfile("tb_rtu_vtype_rtl.vcd");
        $dumpvars(0, tb_rtu_vtype_rtl);
    end

endmodule

verification/tb_rtu_vtype_rtl.vcd
$date
	Fri Apr 03 23:39:47 2026
$end
$version
	Icarus Verilog
$end
$timescale
	1s
$end
$scope module tb_rtu_vtype_rtl $end
$var wire 64 ! cp0_rdata [63:0] $end
$var wire 1 " vill $end
$var wire 3 # vlmul [2:0] $end
$var wire 1 $ vma $end
$var wire 3 % vsew [2:0] $end
$var wire 1 & vta $end
$var reg 1 ' clk $end
$var reg 12 ( cp0_addr [11:0] $end
$var reg 64 ) cp0_wdata [63:0] $end
$var reg 1 * cp0_wen $end
$var reg 42 + create_data [41:0] $end
$var reg 1 , create_en $end
$var reg 1 - rst_b $end
$var reg 1 . vill_reg $end
$var reg 32 / vl_reg [31:0] $end
$var reg 3 0 vlmul_reg [2:0] $end
$var reg 1 1 vma_reg $end
$var reg 3 2 vsew_reg [2:0] $end
$var reg 7 3 vstart_reg [6:0] $end
$var reg 1 4 vta_reg $end
$var reg 64 5 vtype_reg [63:0] $end
$var integer 32 6 fail_count [31:0] $end
$var integer 32 7 pass_count [31:0] $end
$var integer 32 8 test_count [31:0] $end
$scope task check_result $end
$var reg 4 9 actual [3:0] $end
$var reg 4 : expected [3:0] $end
$upscope $end
$scope task check_result_wide $end
$var reg 64 ; actual [63:0] $end
$var reg 64 < expected [63:0] $end
$upscope $end
$scope task create_rob_entry $end
$var reg 42 = data [41:0] $end
$upscope $end
$scope task write_vtype $end
$var reg 64 > data [63:0] $end
$upscope $end
$upscope $end
$enddefinitions $end
$comment Show the parameter values. $end
$dumpall
$end
#0
$dumpvars
bx >
bx =
bx <
bx ;
bx :
bx 9
b0 8
b0 7
b0 6
bx 5
x4
bx 3
bx 2
x1
bx 0
bx /
x.
0-
0,
b0 +
0*
b0 )
b0 (
0'
x&
bx %
x$
bx #
x"
bx !
$end
#5
b0 3
b0 /
0"
0.
b0 %
b0 2
0&
04
0$
01
b0 #
b0 0
b0 !
b0 5
1'
#10
0'
#15
1'
#20
0'
1-
#25
1'
#30
0'
#35
1'
#40
0'
#45
1'
#50
0'
#55
1'
#60
0'
#65
b101 >
1'
#70
0'
#75
1*
b101 )
b110000100001 (
1'
#80
0'
#85
b101 #
b101 0
b101 !
b101 5
0*
1'
#90
0'
#95
1'
#100
0'
#105
b110 >
b11 7
b11 8
b0 :
b0 9
1'
#110
0'
#115
1*
b110 )
1'
#120
0'
#125
b110 #
b110 0
b110 !
b110 5
0*
1'
#130
0'
#135
1'
#140
0'
#145
b111 >
b100 7
b100 8
b110 :
b110 9
1'
#150
0'
#155
1*
b111 )
1'
#160
0'
#165
b111 #
b111 0
b111 !
b111 5
0*
1'
#170
0'
#175
1'
#180
0'
#185
b0 >
b101 7
b101 8
b111 :
b111 9
1'
#190
0'
#195
1*
b0 )
1'
#200
0'
#205
b0 #
b0 0
b0 !
b0 5
0*
1'
#210
0'
#215
1'
#220
0'
#225
b1000 >
b110 7
b110 8
b0 :
b0 9
1'
#230
0'
#235
1*
b1000 )
1'
#240
0'
#245
b1 %
b1 2
b1000 !
b1000 5
0*
1'
#250
0'
#255
1'
#260
0'
#265
b10010000 >
b1 9
b10 6
b1000 8
b11 :
1'
#270
0'
#275
1*
b10010000 )
1'
#280
0'
#285
b10 %
b10 2
1$
11
b10010000 !
b10010000 5
0*
1'
#290
0'
#295
1'
#300
0'
#305
b1010000 >
b0 9
b1000 7
b1010 8
b0 :
1'
#310
0'
#315
1*
b1010000 )
1'
#320
0'
#325
1&
14
0$
01
b1010000 !
b1010000 5
0*
1'
#330
0'
#335
1'
#340
0'
#345
b11000000 >
b1 :
b1 9
b1010 7
b1100 8
1'
#350
0'
#355
1*
b11000000 )
1'
#360
0'
#365
b0 %
b0 2
1$
11
b11000000 !
b11000000 5
0*
1'
#370
0'
#375
1'
#380
0'
#385
b0 >
b1100 7
b1110 8
1'
#390
0'
#395
1*
b0 )
1'
#400
0'
#405
0&
04
0$
01
b0 !
b0 5
0*
1'
#410
0'
#415
1'
#420
0'
#425
b1000 >
b1101 7
b1111 8
b0 :
b0 9
1'
#430
0'
#435
1*
b1000 )
1'
#440
0'
#445
b1 %
b1 2
b1000 !
b1000 5
0*
1'
#450
0'
#455
1'
#460
0'
#465
b10000 >
b1110 7
b10000 8
b1 :
b1 9
1'
#470
0'
#475
1*
b10000 )
1'
#480
0'
#485
b10 %
b10 2
b10000 !
b10000 5
0*
1'
#490
0'
#495
1'
#500
0'
#505
b11000 >
b1111 7
b10001 8
b10 :
b10 9
1'
#510
0'
#515
1*
b11000 )
1'
#520
0'
#525
b11 %
b11 2
b11000 !
b11000 5
0*
1'
#530
0'
#535
1'
#540
0'
#545
b0 >
b10000 7
b10010 8
b11 :
b11 9
1'
#550
0'
#555
1*
b0 )
1'
#560
0'
#565
b0 %
b0 2
b0 !
b0 5
0*
1'
#570
0'
#575
1'
#580
0'
#585
b1111111111111111111111111111111111111111111111111111111111111111 >
b0 :
b0 9
b10011 7
b10101 8
b0 <
b0 ;
1'
#590
0'
#595
1*
b1111111111111111111111111111111111111111111111111111111111111111 )
1'
#600
0'
#605
b111 #
b111 0
b111 %
b111 2
1&
14
1$
11
1"
1.
b1111111111111111111111111111111111111111111111111111111111111111 !
b1111111111111111111111111111111111111111111111111111111111111111 5
0*
1'
#610
0'
#615
1'
#620
0'
#625
b1000000000000000000000000000000000000000000000000000000000000000 >
b10100 7
b10110 8
b1 :
b1 9
1'
#630
0'
#635
1*
b1000000000000000000000000000000000000000000000000000000000000000 )
1'
#640
0'
#645
b0 #
b0 0
b0 %
b0 2
0&
04
0$
01
b1000000000000000000000000000000000000000000000000000000000000000 !
b1000000000000000000000000000000000000000000000000000000000000000 5
0*
1'
#650
0'
#655
1'
#660
0'
#665
b11111111000000000000000000000000000000000000000000000000 >
b0 :
b0 9
b10110 7
b11000 8
1'
#670
0'
#675
1*
b11111111000000000000000000000000000000000000000000000000 )
1'
#680
0'
#685
0"
0.
b11111111000000000000000000000000000000000000000000000000 !
b11111111000000000000000000000000000000000000000000000000 5
0*
1'
#690
0'
#695
1'
#700
0'
#705
b10100010000000000000000000 =
b11000 7
b11010 8
1'
#710
0'
#715
1,
b10100010000000000000000000 +
1'
#720
0'
#725
1&
14
b1 #
b1 0
0,
1'
#730
0'
#735
b1111011000000000000000000 =
b11 6
b11011 8
b101 :
b1 9
1'
#740
0'
#745
1,
b1111011000000000000000000 +
1'
#750
0'
#755
b110 %
b110 2
0&
04
b0 #
b0 0
0,
1'
#760
0'
#765
b101 >
b111 6
b11111 8
b11 :
b110 9
1'
#770
0'
#775
1*
b101 )
1'
#780
0'
#785
b101 #
b101 0
b0 %
b0 2
b101 !
b101 5
0*
1'
#790
0'
#795
1'
#800
0'
#805
b11011 >
b11010 7
b100001 8
b101 :
b101 9
1'
#810
0'
#815
1*
b11011 )
1'
#820
0'
#825
b11 #
b11 0
b11 %
b11 2
b11011 !
b11011 5
0*
1'
#830
0'
#835
1'
#840
0'
#845
b11100 7
b100011 8
b11 :
b11 9
1'
