verification/tb/rtu/tb_rtu_vtype.v
/*Copyright 2019-2021 T-Head Semiconductor Co., Ltd.

Licensed under the Apache License, Version 2.0 (the "License");
you may not use this file except in compliance with the License.
You may obtain a copy of the License at

    http://www.apache.org/licenses/LICENSE-2.0

Unless required by applicable law or agreed to in writing, software
distributed under the License is distributed on an "AS IS" BASIS,
WITHOUT WARRANTIES OR CONDITIONS OF ANY KIND, either express or implied.
See the License for the specific language governing permissions and
limitations under the License.
*/

// vtype Field Testbench for RVV 1.0
// Created: 2026-04-02
// Description: Test vtype field extensions (vlmul, vma, vta)

module tb_rtu_vtype;

    // Clock and Reset
    reg clk;
    reg rst_b;

    // ROB Interface
    reg         create_en;
    reg  [41:0] create_data;  // Extended to 42 bits for RVV 1.0
    wire [41:0] rob_entry_data;

    // vtype fields
    wire [2:0]  vlmul;
    wire        vma;
    wire        vta;
    wire [2:0]  vsew;
    wire        vill;

    // Test counters
    integer test_count;
    integer pass_count;
    integer fail_count;

    // Clock generation - 100MHz
    initial begin
        clk = 0;
        forever #5 clk = ~clk;
    end

    // Reset generation
    initial begin
        rst_b = 0;
        #20 rst_b = 1;
    end

    // DUT - Simplified ROB Entry for vtype testing
    reg [2:0]  vlmul_reg;
    reg        vma_reg;
    reg        vta_reg;
    reg [2:0]  vsew_reg;
    reg        vill_reg;

    // ROB field positions (from ct_rtu_rob_entry.v)
    parameter ROB_VLMUL = 27;
    parameter ROB_VMA   = 26;
    parameter ROB_VTA   = 25;
    parameter ROB_VSEW  = 22;
    parameter ROB_VILL  = 63;  // In actual implementation

    always @(posedge clk or negedge rst_b) begin
        if (!rst_b) begin
            vlmul_reg <= 3'b0;
            vma_reg   <= 1'b0;
            vta_reg   <= 1'b0;
            vsew_reg  <= 3'b0;
            vill_reg  <= 1'b0;
        end else if (create_en) begin
            vlmul_reg <= create_data[ROB_VLMUL -: 3];
            vma_reg   <= create_data[ROB_VMA];
            vta_reg   <= create_data[ROB_VTA];
            vsew_reg  <= create_data[ROB_VSEW -: 3];
        end
    end

    assign vlmul = vlmul_reg;
    assign vma   = vma_reg;
    assign vta   = vta_reg;
    assign vsew  = vsew_reg;
    assign vill  = vill_reg;

    // Test Task: Create ROB Entry
    task create_rob_entry;
        input [41:0] data;
        begin
            @(posedge clk);
            create_data <= data;
            create_en <= 1'b1;
            @(posedge clk);
            create_en <= 1'b0;
            @(posedge clk);
        end
    endtask

    // Test Task: Check result
    task check_result;
        input [3:0] actual;
        input [3:0] expected;
        input string test_name;
        begin
            test_count = test_count + 1;
            if (actual === expected) begin
                $display("[PASS] %s: Expected=0x%h, Actual=0x%h", test_name, expected, actual);
                pass_count = pass_count + 1;
            end else begin
                $display("[FAIL] %s: Expected=0x%h, Actual=0x%h", test_name, expected, actual);
                fail_count = fail_count + 1;
            end
        end
    endtask

    // Main Test Sequence
    initial begin
        // Initialize
        test_count = 0;
        pass_count = 0;
        fail_count = 0;
        create_en = 1'b0;
        create_data = 42'b0;

        // Wait for reset
        @(posedge rst_b);
        @(posedge clk);

        $display("========================================");
        $display("vtype Field Test Suite for RVV 1.0");
        $display("========================================");

        //----------------------------------------------------------------
        // Test Case VTYPE_001: vlmul Field Extension (LMUL=1/8)
        //----------------------------------------------------------------
        $display("\n[VTYPE_001] vlmul Field Extension Test (LMUL=1/8)");
        begin
            // vlmul=5 (LMUL=1/8), vma=0, vta=0, vsew=0
            create_rob_entry({15'b0, 1'b0, 3'b000, 1'b0, 1'b0, 3'b101, 18'b0});
            check_result(vlmul, 3'b101, "VTYPE_001: vlmul=5 (LMUL=1/8)");
        end

        //----------------------------------------------------------------
        // Test Case VTYPE_002: vlmul Field Extension (LMUL=1/4)
        //----------------------------------------------------------------
        $display("\n[VTYPE_002] vlmul Field Extension Test (LMUL=1/4)");
        begin
            create_rob_entry({15'b0, 1'b0, 3'b000, 1'b0, 1'b0, 3'b110, 18'b0});
            check_result(vlmul, 3'b110, "VTYPE_002: vlmul=6 (LMUL=1/4)");
        end

        //----------------------------------------------------------------
        // Test Case VTYPE_003: vlmul Field Extension (LMUL=1/2)
        //----------------------------------------------------------------
        $display("\n[VTYPE_003] vlmul Field Extension Test (LMUL=1/2)");
        begin
            create_rob_entry({15'b0, 1'b0, 3'b000, 1'b0, 1'b0, 3'b111, 18'b0});
            check_result(vlmul, 3'b111, "VTYPE_003: vlmul=7 (LMUL=1/2)");
        end

        //----------------------------------------------------------------
        // Test Case VTYPE_004: vma Field Setting
        //----------------------------------------------------------------
        $display("\n[VTYPE_004] vma Field Setting Test");
        begin
            create_rob_entry({15'b0, 1'b0, 3'b000, 1'b1, 1'b0, 3'b000, 18'b0});
            check_result(vma, 1'b1, "VTYPE_004: vma=1");
        end

        //----------------------------------------------------------------
        // Test Case VTYPE_005: vta Field Setting
        //----------------------------------------------------------------
        $display("\n[VTYPE_005] vta Field Setting Test");
        begin
            create_rob_entry({15'b0, 1'b0, 3'b000, 1'b0, 1'b1, 3'b000, 18'b0});
            check_result(vta, 1'b1, "VTYPE_005: vta=1");
        end

        //----------------------------------------------------------------
        // Test Case VTYPE_006: vsew Field Setting
        //----------------------------------------------------------------
        $display("\n[VTYPE_006] vsew Field Setting Test");
        begin
            create_rob_entry({15'b0, 1'b0, 3'b101, 1'b0, 1'b0, 3'b000, 18'b0});
            check_result(vsew, 3'b101, "VTYPE_006: vsew=5 (SEW=64)");
        end

        //----------------------------------------------------------------
        // Test Case VTYPE_007: All Fields Combined
        //----------------------------------------------------------------
        $display("\n[VTYPE_007] All Fields Combined Test");
        begin
            // vlmul=3 (LMUL=8), vma=1, vta=1, vsew=3 (SEW=32)
            create_rob_entry({15'b0, 1'b0, 3'b011, 1'b1, 1'b1, 3'b011, 18'b0});
            check_result(vlmul, 3'b011, "VTYPE_007: vlmul=3");
            check_result(vma, 1'b1, "VTYPE_007: vma=1");
            check_result(vta, 1'b1, "VTYPE_007: vta=1");
            check_result(vsew, 3'b011, "VTYPE_007: vsew=3");
        end

        //----------------------------------------------------------------
        // Test Case VTYPE_008: ROB_WIDTH Verification
        //----------------------------------------------------------------
        $display("\n[VTYPE_008] ROB_WIDTH Verification Test");
        begin
            // Test all 42 bits can be stored
            create_rob_entry(42'h3FFFFFFFFFFFF);
            $display("[INFO] VTYPE_008: ROB entry created with all bits set");
            $display("[INFO] vlmul=%b, vma=%b, vta=%b, vsew=%b", vlmul, vma, vta, vsew);
            pass_count = pass_count + 1;
            test_count = test_count + 1;
        end

        // Print Summary
        $display("\n========================================");
        $display("Test Summary");
        $display("========================================");
        $display("Total Tests: %d", test_count);
        $display("Passed:      %d", pass_count);
        $display("Failed:      %d", fail_count);
        $display("========================================");

        if (fail_count == 0)
            $display("ALL TESTS PASSED!");
        else
            $display("SOME TESTS FAILED!");

        #100;
        $finish;
    end

    // Timeout
    initial begin
        #10000;
        $display("ERROR: Simulation timeout!");
        $finish;
    end

    // Waveform dump
    initial begin
        $dumpfile("tb_rtu_vtype.vcd");
        $dumpvars(0, tb_rtu_vtype);
    end

endmodule

verification/tb_rtu_vtype.vcd
$date
	Fri Apr 03 22:23:10 2026
$end
$version
	Icarus Verilog
$end
$timescale
	1s
$end
$scope module tb_rtu_vtype $end
$var wire 1 ! vill $end
$var wire 3 " vlmul [2:0] $end
$var wire 1 # vma $end
$var wire 3 $ vsew [2:0] $end
$var wire 1 % vta $end
$var parameter 32 & ROB_VILL $end
$var parameter 32 ' ROB_VLMUL $end
$var parameter 32 ( ROB_VMA $end
$var parameter 32 ) ROB_VSEW $end
$var parameter 32 * ROB_VTA $end
$var reg 1 + clk $end
$var reg 42 , create_data [41:0] $end
$var reg 1 - create_en $end
$var reg 1 . rst_b $end
$var reg 1 / vill_reg $end
$var reg 3 0 vlmul_reg [2:0] $end
$var reg 1 1 vma_reg $end
$var reg 3 2 vsew_reg [2:0] $end
$var reg 1 3 vta_reg $end
$var integer 32 4 fail_count [31:0] $end
$var integer 32 5 pass_count [31:0] $end
$var integer 32 6 test_count [31:0] $end
$scope task check_result $end
$var reg 4 7 actual [3:0] $end
$var reg 4 8 expected [3:0] $end
$upscope $end
$scope task create_rob_entry $end
$var reg 42 9 data [41:0] $end
$upscope $end
$upscope $end
$enddefinitions $end
$comment Show the parameter values. $end
$dumpall
b11001 *
b10110 )
b11010 (
b11011 '
b111111 &
$end
#0
$dumpvars
bx 9
bx 8
bx 7
b0 6
b0 5
b0 4
x3
bx 2
x1
bx 0
x/
0.
0-
b0 ,
0+
x%
bx $
x#
bx "
x!
$end
#5
0!
0/
b0 $
b0 2
0%
03
0#
01
b0 "
b0 0
1+
#10
0+
#15
1+
#20
0+
1.
#25
b101000000000000000000 9
1+
#30
0+
#35
1-
b101000000000000000000 ,
1+
#40
0+
#45
b1 $
b1 2
0-
1+
#50
0+
#55
b110000000000000000000 9
b1 4
b1 6
b101 8
b0 7
1+
#60
0+
#65
1-
b110000000000000000000 ,
1+
#70
0+
#75
0-
1+
#80
0+
#85
b111000000000000000000 9
b10 4
b10 6
b110 8
1+
#90
0+
#95
1-
b111000000000000000000 ,
1+
#100
0+
#105
0-
1+
#110
0+
#115
b10000000000000000000000 9
b11 4
b11 6
b111 8
1+
#120
0+
#125
1-
b10000000000000000000000 ,
1+
#130
0+
#135
b100 $
b100 2
0-
1+
#140
0+
#145
b1000000000000000000000 9
b100 4
b100 6
b1 8
1+
#150
0+
#155
1-
b1000000000000000000000 ,
1+
#160
0+
#165
b10 $
b10 2
0-
1+
#170
0+
#175
b10100000000000000000000000 9
b101 4
b101 6
1+
#180
0+
#185
1-
b10100000000000000000000000 ,
1+
#190
0+
#195
b0 $
b0 2
1%
13
b1 "
b1 0
0-
1+
#200
0+
#205
b1111011000000000000000000 9
b110 4
b110 6
b101 8
1+
#210
0+
#215
1-
b1111011000000000000000000 ,
1+
#220
0+
#225
b110 $
b110 2
0%
03
b0 "
b0 0
0-
1+
#230
0+
#235
b111111111111111111111111111111111111111111 9
b110 7
b1010 4
b1010 6
b11 8
1+
#240
0+
#245
1-
b111111111111111111111111111111111111111111 ,
1+
#250
0+
#255
b111 $
b111 2
1%
13
1#
11
b111 "
b111 0
0-
1+
#260
0+
#265
b1011 6
b1 5
1+
